[{"species_id":"638","version_id":"17","language_id":"9","flavor_text":"This legendary Pokémon battled against\r\nhumans to protect Pokémon.\r\nIts personality is calm and composed."},{"species_id":"638","version_id":"18","language_id":"9","flavor_text":"It has a body and heart of steel.\r\nIts glare is sufficient to make even\r\nan unruly Pokémon obey it."},{"species_id":"638","version_id":"21","language_id":"9","flavor_text":"It has a body and heart of steel.\r\nIt worked with its allies to punish\r\npeople when they hurt Pokémon."},{"species_id":"638","version_id":"22","language_id":"9","flavor_text":"It has a body and heart of steel.\r\nIt worked with its allies to punish\r\npeople when they hurt Pokémon."}]