[{"id":"101","version_id":"12","location_area_id":"6","encounter_slot_id":"1","pokemon_id":"74","min_level":"6","max_level":"6"},{"id":"102","version_id":"12","location_area_id":"6","encounter_slot_id":"2","pokemon_id":"74","min_level":"6","max_level":"6"},{"id":"105","version_id":"12","location_area_id":"6","encounter_slot_id":"5","pokemon_id":"74","min_level":"7","max_level":"7"},{"id":"106","version_id":"12","location_area_id":"6","encounter_slot_id":"6","pokemon_id":"74","min_level":"7","max_level":"7"},{"id":"109","version_id":"12","location_area_id":"6","encounter_slot_id":"9","pokemon_id":"74","min_level":"9","max_level":"9"},{"id":"110","version_id":"12","location_area_id":"6","encounter_slot_id":"10","pokemon_id":"74","min_level":"9","max_level":"9"},{"id":"111","version_id":"12","location_area_id":"6","encounter_slot_id":"11","pokemon_id":"74","min_level":"5","max_level":"5"},{"id":"112","version_id":"12","location_area_id":"6","encounter_slot_id":"12","pokemon_id":"74","min_level":"5","max_level":"5"},{"id":"113","version_id":"12","location_area_id":"7","encounter_slot_id":"1","pokemon_id":"74","min_level":"7","max_level":"7"},{"id":"114","version_id":"12","location_area_id":"7","encounter_slot_id":"2","pokemon_id":"74","min_level":"7","max_level":"7"},{"id":"117","version_id":"12","location_area_id":"7","encounter_slot_id":"5","pokemon_id":"74","min_level":"8","max_level":"8"},{"id":"118","version_id":"12","location_area_id":"7","encounter_slot_id":"6","pokemon_id":"74","min_level":"8","max_level":"8"},{"id":"121","version_id":"12","location_area_id":"7","encounter_slot_id":"9","pokemon_id":"74","min_level":"10","max_level":"10"},{"id":"122","version_id":"12","location_area_id":"7","encounter_slot_id":"10","pokemon_id":"74","min_level":"10","max_level":"10"},{"id":"123","version_id":"12","location_area_id":"7","encounter_slot_id":"11","pokemon_id":"74","min_level":"6","max_level":"6"},{"id":"124","version_id":"12","location_area_id":"7","encounter_slot_id":"12","pokemon_id":"74","min_level":"6","max_level":"6"},{"id":"244","version_id":"12","location_area_id":"11","encounter_slot_id":"2","pokemon_id":"74","min_level":"15","max_level":"15"},{"id":"246","version_id":"12","location_area_id":"11","encounter_slot_id":"3","pokemon_id":"74","min_level":"14","max_level":"14"},{"id":"247","version_id":"12","location_area_id":"11","encounter_slot_id":"3","pokemon_id":"74","min_level":"14","max_level":"14"},{"id":"526","version_id":"12","location_area_id":"22","encounter_slot_id":"2","pokemon_id":"74","min_level":"13","max_level":"13"},{"id":"528","version_id":"12","location_area_id":"22","encounter_slot_id":"3","pokemon_id":"74","min_level":"12","max_level":"12"},{"id":"529","version_id":"12","location_area_id":"22","encounter_slot_id":"3","pokemon_id":"74","min_level":"12","max_level":"12"},{"id":"1164","version_id":"12","location_area_id":"54","encounter_slot_id":"3","pokemon_id":"74","min_level":"5","max_level":"5"},{"id":"1165","version_id":"12","location_area_id":"54","encounter_slot_id":"4","pokemon_id":"74","min_level":"5","max_level":"5"},{"id":"1194","version_id":"12","location_area_id":"55","encounter_slot_id":"1","pokemon_id":"74","min_level":"5","max_level":"5"},{"id":"1195","version_id":"12","location_area_id":"55","encounter_slot_id":"2","pokemon_id":"74","min_level":"5","max_level":"5"},{"id":"1198","version_id":"12","location_area_id":"55","encounter_slot_id":"5","pokemon_id":"74","min_level":"6","max_level":"6"},{"id":"1199","version_id":"12","location_area_id":"55","encounter_slot_id":"6","pokemon_id":"74","min_level":"6","max_level":"6"},{"id":"1200","version_id":"12","location_area_id":"55","encounter_slot_id":"7","pokemon_id":"74","min_level":"7","max_level":"7"},{"id":"1201","version_id":"12","location_area_id":"55","encounter_slot_id":"8","pokemon_id":"74","min_level":"7","max_level":"7"},{"id":"1202","version_id":"12","location_area_id":"55","encounter_slot_id":"9","pokemon_id":"74","min_level":"8","max_level":"8"},{"id":"1203","version_id":"12","location_area_id":"55","encounter_slot_id":"10","pokemon_id":"74","min_level":"8","max_level":"8"},{"id":"1204","version_id":"12","location_area_id":"55","encounter_slot_id":"11","pokemon_id":"74","min_level":"4","max_level":"4"},{"id":"1205","version_id":"12","location_area_id":"55","encounter_slot_id":"12","pokemon_id":"74","min_level":"4","max_level":"4"},{"id":"1209","version_id":"12","location_area_id":"56","encounter_slot_id":"4","pokemon_id":"74","min_level":"9","max_level":"9"},{"id":"1276","version_id":"12","location_area_id":"58","encounter_slot_id":"9","pokemon_id":"74","min_level":"25","max_level":"25"},{"id":"1277","version_id":"12","location_area_id":"58","encounter_slot_id":"9","pokemon_id":"74","min_level":"25","max_level":"25"},{"id":"1278","version_id":"12","location_area_id":"58","encounter_slot_id":"9","pokemon_id":"74","min_level":"25","max_level":"25"},{"id":"1279","version_id":"12","location_area_id":"58","encounter_slot_id":"9","pokemon_id":"74","min_level":"25","max_level":"25"},{"id":"1280","version_id":"12","location_area_id":"58","encounter_slot_id":"9","pokemon_id":"74","min_level":"25","max_level":"25"},{"id":"1288","version_id":"12","location_area_id":"58","encounter_slot_id":"11","pokemon_id":"74","min_level":"27","max_level":"27"},{"id":"1298","version_id":"12","location_area_id":"59","encounter_slot_id":"9","pokemon_id":"74","min_level":"27","max_level":"27"},{"id":"1299","version_id":"12","location_area_id":"59","encounter_slot_id":"9","pokemon_id":"74","min_level":"27","max_level":"27"},{"id":"1300","version_id":"12","location_area_id":"59","encounter_slot_id":"9","pokemon_id":"74","min_level":"27","max_level":"27"},{"id":"1301","version_id":"12","location_area_id":"59","encounter_slot_id":"9","pokemon_id":"74","min_level":"27","max_level":"27"},{"id":"1302","version_id":"12","location_area_id":"59","encounter_slot_id":"9","pokemon_id":"74","min_level":"27","max_level":"27"},{"id":"1310","version_id":"12","location_area_id":"59","encounter_slot_id":"11","pokemon_id":"74","min_level":"29","max_level":"29"},{"id":"2444","version_id":"12","location_area_id":"113","encounter_slot_id":"3","pokemon_id":"74","min_level":"15","max_level":"15"},{"id":"2450","version_id":"12","location_area_id":"113","encounter_slot_id":"9","pokemon_id":"74","min_level":"16","max_level":"16"},{"id":"2451","version_id":"12","location_area_id":"113","encounter_slot_id":"9","pokemon_id":"74","min_level":"16","max_level":"16"},{"id":"2452","version_id":"12","location_area_id":"113","encounter_slot_id":"9","pokemon_id":"74","min_level":"16","max_level":"16"},{"id":"2453","version_id":"12","location_area_id":"113","encounter_slot_id":"9","pokemon_id":"74","min_level":"16","max_level":"16"},{"id":"2454","version_id":"12","location_area_id":"113","encounter_slot_id":"9","pokemon_id":"74","min_level":"16","max_level":"16"},{"id":"2462","version_id":"12","location_area_id":"113","encounter_slot_id":"11","pokemon_id":"74","min_level":"16","max_level":"16"},{"id":"2466","version_id":"12","location_area_id":"114","encounter_slot_id":"3","pokemon_id":"74","min_level":"16","max_level":"16"},{"id":"2486","version_id":"12","location_area_id":"115","encounter_slot_id":"1","pokemon_id":"74","min_level":"22","max_level":"22"},{"id":"2487","version_id":"12","location_area_id":"115","encounter_slot_id":"2","pokemon_id":"74","min_level":"22","max_level":"22"},{"id":"2488","version_id":"12","location_area_id":"115","encounter_slot_id":"3","pokemon_id":"74","min_level":"22","max_level":"22"},{"id":"2489","version_id":"12","location_area_id":"115","encounter_slot_id":"4","pokemon_id":"74","min_level":"22","max_level":"22"},{"id":"2490","version_id":"12","location_area_id":"115","encounter_slot_id":"5","pokemon_id":"74","min_level":"22","max_level":"22"},{"id":"2491","version_id":"12","location_area_id":"115","encounter_slot_id":"6","pokemon_id":"74","min_level":"22","max_level":"22"},{"id":"2492","version_id":"12","location_area_id":"115","encounter_slot_id":"7","pokemon_id":"74","min_level":"22","max_level":"22"},{"id":"2493","version_id":"12","location_area_id":"115","encounter_slot_id":"8","pokemon_id":"74","min_level":"22","max_level":"22"},{"id":"2494","version_id":"12","location_area_id":"115","encounter_slot_id":"9","pokemon_id":"74","min_level":"22","max_level":"22"},{"id":"2496","version_id":"12","location_area_id":"115","encounter_slot_id":"11","pokemon_id":"74","min_level":"22","max_level":"22"},{"id":"2498","version_id":"12","location_area_id":"116","encounter_slot_id":"1","pokemon_id":"74","min_level":"23","max_level":"23"},{"id":"2499","version_id":"12","location_area_id":"116","encounter_slot_id":"2","pokemon_id":"74","min_level":"23","max_level":"23"},{"id":"2500","version_id":"12","location_area_id":"116","encounter_slot_id":"3","pokemon_id":"74","min_level":"23","max_level":"23"},{"id":"2501","version_id":"12","location_area_id":"116","encounter_slot_id":"4","pokemon_id":"74","min_level":"23","max_level":"23"},{"id":"2502","version_id":"12","location_area_id":"116","encounter_slot_id":"5","pokemon_id":"74","min_level":"23","max_level":"23"},{"id":"2503","version_id":"12","location_area_id":"116","encounter_slot_id":"6","pokemon_id":"74","min_level":"23","max_level":"23"},{"id":"2504","version_id":"12","location_area_id":"116","encounter_slot_id":"7","pokemon_id":"74","min_level":"23","max_level":"23"},{"id":"2506","version_id":"12","location_area_id":"116","encounter_slot_id":"9","pokemon_id":"74","min_level":"23","max_level":"23"},{"id":"2508","version_id":"12","location_area_id":"116","encounter_slot_id":"11","pokemon_id":"74","min_level":"23","max_level":"23"},{"id":"2510","version_id":"12","location_area_id":"117","encounter_slot_id":"1","pokemon_id":"74","min_level":"24","max_level":"24"},{"id":"2511","version_id":"12","location_area_id":"117","encounter_slot_id":"2","pokemon_id":"74","min_level":"24","max_level":"24"},{"id":"2512","version_id":"12","location_area_id":"117","encounter_slot_id":"3","pokemon_id":"74","min_level":"24","max_level":"24"},{"id":"2513","version_id":"12","location_area_id":"117","encounter_slot_id":"4","pokemon_id":"74","min_level":"24","max_level":"24"},{"id":"2514","version_id":"12","location_area_id":"117","encounter_slot_id":"5","pokemon_id":"74","min_level":"24","max_level":"24"},{"id":"2516","version_id":"12","location_area_id":"117","encounter_slot_id":"7","pokemon_id":"74","min_level":"24","max_level":"24"},{"id":"2518","version_id":"12","location_area_id":"117","encounter_slot_id":"9","pokemon_id":"74","min_level":"24","max_level":"24"},{"id":"2520","version_id":"12","location_area_id":"117","encounter_slot_id":"11","pokemon_id":"74","min_level":"24","max_level":"24"},{"id":"2558","version_id":"12","location_area_id":"120","encounter_slot_id":"1","pokemon_id":"74","min_level":"30","max_level":"30"},{"id":"2562","version_id":"12","location_area_id":"120","encounter_slot_id":"5","pokemon_id":"74","min_level":"29","max_level":"29"},{"id":"2566","version_id":"12","location_area_id":"120","encounter_slot_id":"9","pokemon_id":"74","min_level":"31","max_level":"31"},{"id":"2568","version_id":"12","location_area_id":"120","encounter_slot_id":"11","pokemon_id":"74","min_level":"31","max_level":"31"},{"id":"2590","version_id":"12","location_area_id":"121","encounter_slot_id":"11","pokemon_id":"74","min_level":"31","max_level":"31"},{"id":"2612","version_id":"12","location_area_id":"122","encounter_slot_id":"11","pokemon_id":"74","min_level":"31","max_level":"31"},{"id":"2634","version_id":"12","location_area_id":"123","encounter_slot_id":"11","pokemon_id":"74","min_level":"31","max_level":"31"},{"id":"2656","version_id":"12","location_area_id":"124","encounter_slot_id":"11","pokemon_id":"74","min_level":"32","max_level":"32"},{"id":"2678","version_id":"12","location_area_id":"125","encounter_slot_id":"11","pokemon_id":"74","min_level":"32","max_level":"32"},{"id":"3083","version_id":"12","location_area_id":"139","encounter_slot_id":"2","pokemon_id":"74","min_level":"20","max_level":"20"},{"id":"3448","version_id":"12","location_area_id":"148","encounter_slot_id":"5","pokemon_id":"74","min_level":"14","max_level":"14"},{"id":"3472","version_id":"12","location_area_id":"149","encounter_slot_id":"2","pokemon_id":"74","min_level":"5","max_level":"5"},{"id":"3480","version_id":"12","location_area_id":"149","encounter_slot_id":"5","pokemon_id":"74","min_level":"6","max_level":"6"},{"id":"3482","version_id":"12","location_area_id":"149","encounter_slot_id":"6","pokemon_id":"74","min_level":"6","max_level":"6"},{"id":"3484","version_id":"12","location_area_id":"149","encounter_slot_id":"7","pokemon_id":"74","min_level":"7","max_level":"7"},{"id":"3485","version_id":"12","location_area_id":"149","encounter_slot_id":"8","pokemon_id":"74","min_level":"7","max_level":"7"},{"id":"3492","version_id":"12","location_area_id":"149","encounter_slot_id":"10","pokemon_id":"74","min_level":"7","max_level":"7"},{"id":"3493","version_id":"12","location_area_id":"149","encounter_slot_id":"10","pokemon_id":"74","min_level":"7","max_level":"7"},{"id":"3494","version_id":"12","location_area_id":"149","encounter_slot_id":"10","pokemon_id":"74","min_level":"7","max_level":"7"},{"id":"3496","version_id":"12","location_area_id":"149","encounter_slot_id":"10","pokemon_id":"74","min_level":"7","max_level":"7"},{"id":"3497","version_id":"12","location_area_id":"149","encounter_slot_id":"10","pokemon_id":"74","min_level":"7","max_level":"7"},{"id":"3500","version_id":"12","location_area_id":"149","encounter_slot_id":"12","pokemon_id":"74","min_level":"7","max_level":"7"},{"id":"3687","version_id":"12","location_area_id":"157","encounter_slot_id":"2","pokemon_id":"74","min_level":"19","max_level":"19"},{"id":"3694","version_id":"12","location_area_id":"157","encounter_slot_id":"5","pokemon_id":"74","min_level":"19","max_level":"19"},{"id":"3774","version_id":"12","location_area_id":"159","encounter_slot_id":"5","pokemon_id":"74","min_level":"13","max_level":"13"},{"id":"3958","version_id":"12","location_area_id":"164","encounter_slot_id":"2","pokemon_id":"74","min_level":"22","max_level":"22"},{"id":"4010","version_id":"12","location_area_id":"165","encounter_slot_id":"2","pokemon_id":"74","min_level":"20","max_level":"20"},{"id":"4015","version_id":"12","location_area_id":"165","encounter_slot_id":"4","pokemon_id":"74","min_level":"21","max_level":"21"},{"id":"4024","version_id":"12","location_area_id":"165","encounter_slot_id":"9","pokemon_id":"74","min_level":"22","max_level":"22"},{"id":"4025","version_id":"12","location_area_id":"165","encounter_slot_id":"9","pokemon_id":"74","min_level":"22","max_level":"22"},{"id":"4026","version_id":"12","location_area_id":"165","encounter_slot_id":"9","pokemon_id":"74","min_level":"22","max_level":"22"},{"id":"4028","version_id":"12","location_area_id":"165","encounter_slot_id":"9","pokemon_id":"74","min_level":"22","max_level":"22"},{"id":"4029","version_id":"12","location_area_id":"165","encounter_slot_id":"9","pokemon_id":"74","min_level":"22","max_level":"22"},{"id":"4036","version_id":"12","location_area_id":"165","encounter_slot_id":"11","pokemon_id":"74","min_level":"22","max_level":"22"},{"id":"4772","version_id":"13","location_area_id":"6","encounter_slot_id":"1","pokemon_id":"74","min_level":"6","max_level":"6"},{"id":"4773","version_id":"13","location_area_id":"6","encounter_slot_id":"2","pokemon_id":"74","min_level":"6","max_level":"6"},{"id":"4776","version_id":"13","location_area_id":"6","encounter_slot_id":"5","pokemon_id":"74","min_level":"7","max_level":"7"},{"id":"4777","version_id":"13","location_area_id":"6","encounter_slot_id":"6","pokemon_id":"74","min_level":"7","max_level":"7"},{"id":"4780","version_id":"13","location_area_id":"6","encounter_slot_id":"9","pokemon_id":"74","min_level":"9","max_level":"9"},{"id":"4781","version_id":"13","location_area_id":"6","encounter_slot_id":"10","pokemon_id":"74","min_level":"9","max_level":"9"},{"id":"4782","version_id":"13","location_area_id":"6","encounter_slot_id":"11","pokemon_id":"74","min_level":"5","max_level":"5"},{"id":"4783","version_id":"13","location_area_id":"6","encounter_slot_id":"12","pokemon_id":"74","min_level":"5","max_level":"5"},{"id":"4784","version_id":"13","location_area_id":"7","encounter_slot_id":"1","pokemon_id":"74","min_level":"7","max_level":"7"},{"id":"4785","version_id":"13","location_area_id":"7","encounter_slot_id":"2","pokemon_id":"74","min_level":"7","max_level":"7"},{"id":"4788","version_id":"13","location_area_id":"7","encounter_slot_id":"5","pokemon_id":"74","min_level":"8","max_level":"8"},{"id":"4789","version_id":"13","location_area_id":"7","encounter_slot_id":"6","pokemon_id":"74","min_level":"8","max_level":"8"},{"id":"4792","version_id":"13","location_area_id":"7","encounter_slot_id":"9","pokemon_id":"74","min_level":"10","max_level":"10"},{"id":"4793","version_id":"13","location_area_id":"7","encounter_slot_id":"10","pokemon_id":"74","min_level":"10","max_level":"10"},{"id":"4794","version_id":"13","location_area_id":"7","encounter_slot_id":"11","pokemon_id":"74","min_level":"6","max_level":"6"},{"id":"4795","version_id":"13","location_area_id":"7","encounter_slot_id":"12","pokemon_id":"74","min_level":"6","max_level":"6"},{"id":"4915","version_id":"13","location_area_id":"11","encounter_slot_id":"2","pokemon_id":"74","min_level":"15","max_level":"15"},{"id":"4917","version_id":"13","location_area_id":"11","encounter_slot_id":"3","pokemon_id":"74","min_level":"14","max_level":"14"},{"id":"4918","version_id":"13","location_area_id":"11","encounter_slot_id":"3","pokemon_id":"74","min_level":"14","max_level":"14"},{"id":"5197","version_id":"13","location_area_id":"22","encounter_slot_id":"2","pokemon_id":"74","min_level":"13","max_level":"13"},{"id":"5199","version_id":"13","location_area_id":"22","encounter_slot_id":"3","pokemon_id":"74","min_level":"12","max_level":"12"},{"id":"5200","version_id":"13","location_area_id":"22","encounter_slot_id":"3","pokemon_id":"74","min_level":"12","max_level":"12"},{"id":"5835","version_id":"13","location_area_id":"54","encounter_slot_id":"3","pokemon_id":"74","min_level":"5","max_level":"5"},{"id":"5836","version_id":"13","location_area_id":"54","encounter_slot_id":"4","pokemon_id":"74","min_level":"5","max_level":"5"},{"id":"5865","version_id":"13","location_area_id":"55","encounter_slot_id":"1","pokemon_id":"74","min_level":"5","max_level":"5"},{"id":"5866","version_id":"13","location_area_id":"55","encounter_slot_id":"2","pokemon_id":"74","min_level":"5","max_level":"5"},{"id":"5869","version_id":"13","location_area_id":"55","encounter_slot_id":"5","pokemon_id":"74","min_level":"6","max_level":"6"},{"id":"5870","version_id":"13","location_area_id":"55","encounter_slot_id":"6","pokemon_id":"74","min_level":"6","max_level":"6"},{"id":"5871","version_id":"13","location_area_id":"55","encounter_slot_id":"7","pokemon_id":"74","min_level":"7","max_level":"7"},{"id":"5872","version_id":"13","location_area_id":"55","encounter_slot_id":"8","pokemon_id":"74","min_level":"7","max_level":"7"},{"id":"5873","version_id":"13","location_area_id":"55","encounter_slot_id":"9","pokemon_id":"74","min_level":"8","max_level":"8"},{"id":"5874","version_id":"13","location_area_id":"55","encounter_slot_id":"10","pokemon_id":"74","min_level":"8","max_level":"8"},{"id":"5875","version_id":"13","location_area_id":"55","encounter_slot_id":"11","pokemon_id":"74","min_level":"4","max_level":"4"},{"id":"5876","version_id":"13","location_area_id":"55","encounter_slot_id":"12","pokemon_id":"74","min_level":"4","max_level":"4"},{"id":"5880","version_id":"13","location_area_id":"56","encounter_slot_id":"4","pokemon_id":"74","min_level":"9","max_level":"9"},{"id":"5947","version_id":"13","location_area_id":"58","encounter_slot_id":"9","pokemon_id":"74","min_level":"25","max_level":"25"},{"id":"5948","version_id":"13","location_area_id":"58","encounter_slot_id":"9","pokemon_id":"74","min_level":"25","max_level":"25"},{"id":"5949","version_id":"13","location_area_id":"58","encounter_slot_id":"9","pokemon_id":"74","min_level":"25","max_level":"25"},{"id":"5950","version_id":"13","location_area_id":"58","encounter_slot_id":"9","pokemon_id":"74","min_level":"25","max_level":"25"},{"id":"5951","version_id":"13","location_area_id":"58","encounter_slot_id":"9","pokemon_id":"74","min_level":"25","max_level":"25"},{"id":"5959","version_id":"13","location_area_id":"58","encounter_slot_id":"11","pokemon_id":"74","min_level":"27","max_level":"27"},{"id":"5969","version_id":"13","location_area_id":"59","encounter_slot_id":"9","pokemon_id":"74","min_level":"27","max_level":"27"},{"id":"5970","version_id":"13","location_area_id":"59","encounter_slot_id":"9","pokemon_id":"74","min_level":"27","max_level":"27"},{"id":"5971","version_id":"13","location_area_id":"59","encounter_slot_id":"9","pokemon_id":"74","min_level":"27","max_level":"27"},{"id":"5972","version_id":"13","location_area_id":"59","encounter_slot_id":"9","pokemon_id":"74","min_level":"27","max_level":"27"},{"id":"5973","version_id":"13","location_area_id":"59","encounter_slot_id":"9","pokemon_id":"74","min_level":"27","max_level":"27"},{"id":"5981","version_id":"13","location_area_id":"59","encounter_slot_id":"11","pokemon_id":"74","min_level":"29","max_level":"29"},{"id":"7115","version_id":"13","location_area_id":"113","encounter_slot_id":"3","pokemon_id":"74","min_level":"15","max_level":"15"},{"id":"7121","version_id":"13","location_area_id":"113","encounter_slot_id":"9","pokemon_id":"74","min_level":"16","max_level":"16"},{"id":"7122","version_id":"13","location_area_id":"113","encounter_slot_id":"9","pokemon_id":"74","min_level":"16","max_level":"16"},{"id":"7123","version_id":"13","location_area_id":"113","encounter_slot_id":"9","pokemon_id":"74","min_level":"16","max_level":"16"},{"id":"7124","version_id":"13","location_area_id":"113","encounter_slot_id":"9","pokemon_id":"74","min_level":"16","max_level":"16"},{"id":"7125","version_id":"13","location_area_id":"113","encounter_slot_id":"9","pokemon_id":"74","min_level":"16","max_level":"16"},{"id":"7133","version_id":"13","location_area_id":"113","encounter_slot_id":"11","pokemon_id":"74","min_level":"16","max_level":"16"},{"id":"7137","version_id":"13","location_area_id":"114","encounter_slot_id":"3","pokemon_id":"74","min_level":"16","max_level":"16"},{"id":"7157","version_id":"13","location_area_id":"115","encounter_slot_id":"1","pokemon_id":"74","min_level":"22","max_level":"22"},{"id":"7158","version_id":"13","location_area_id":"115","encounter_slot_id":"2","pokemon_id":"74","min_level":"22","max_level":"22"},{"id":"7159","version_id":"13","location_area_id":"115","encounter_slot_id":"3","pokemon_id":"74","min_level":"22","max_level":"22"},{"id":"7160","version_id":"13","location_area_id":"115","encounter_slot_id":"4","pokemon_id":"74","min_level":"22","max_level":"22"},{"id":"7161","version_id":"13","location_area_id":"115","encounter_slot_id":"5","pokemon_id":"74","min_level":"22","max_level":"22"},{"id":"7162","version_id":"13","location_area_id":"115","encounter_slot_id":"6","pokemon_id":"74","min_level":"22","max_level":"22"},{"id":"7163","version_id":"13","location_area_id":"115","encounter_slot_id":"7","pokemon_id":"74","min_level":"22","max_level":"22"},{"id":"7164","version_id":"13","location_area_id":"115","encounter_slot_id":"8","pokemon_id":"74","min_level":"22","max_level":"22"},{"id":"7165","version_id":"13","location_area_id":"115","encounter_slot_id":"9","pokemon_id":"74","min_level":"22","max_level":"22"},{"id":"7167","version_id":"13","location_area_id":"115","encounter_slot_id":"11","pokemon_id":"74","min_level":"22","max_level":"22"},{"id":"7169","version_id":"13","location_area_id":"116","encounter_slot_id":"1","pokemon_id":"74","min_level":"23","max_level":"23"},{"id":"7170","version_id":"13","location_area_id":"116","encounter_slot_id":"2","pokemon_id":"74","min_level":"23","max_level":"23"},{"id":"7171","version_id":"13","location_area_id":"116","encounter_slot_id":"3","pokemon_id":"74","min_level":"23","max_level":"23"},{"id":"7172","version_id":"13","location_area_id":"116","encounter_slot_id":"4","pokemon_id":"74","min_level":"23","max_level":"23"},{"id":"7173","version_id":"13","location_area_id":"116","encounter_slot_id":"5","pokemon_id":"74","min_level":"23","max_level":"23"},{"id":"7174","version_id":"13","location_area_id":"116","encounter_slot_id":"6","pokemon_id":"74","min_level":"23","max_level":"23"},{"id":"7175","version_id":"13","location_area_id":"116","encounter_slot_id":"7","pokemon_id":"74","min_level":"23","max_level":"23"},{"id":"7177","version_id":"13","location_area_id":"116","encounter_slot_id":"9","pokemon_id":"74","min_level":"23","max_level":"23"},{"id":"7179","version_id":"13","location_area_id":"116","encounter_slot_id":"11","pokemon_id":"74","min_level":"23","max_level":"23"},{"id":"7181","version_id":"13","location_area_id":"117","encounter_slot_id":"1","pokemon_id":"74","min_level":"24","max_level":"24"},{"id":"7182","version_id":"13","location_area_id":"117","encounter_slot_id":"2","pokemon_id":"74","min_level":"24","max_level":"24"},{"id":"7183","version_id":"13","location_area_id":"117","encounter_slot_id":"3","pokemon_id":"74","min_level":"24","max_level":"24"},{"id":"7184","version_id":"13","location_area_id":"117","encounter_slot_id":"4","pokemon_id":"74","min_level":"24","max_level":"24"},{"id":"7185","version_id":"13","location_area_id":"117","encounter_slot_id":"5","pokemon_id":"74","min_level":"24","max_level":"24"},{"id":"7187","version_id":"13","location_area_id":"117","encounter_slot_id":"7","pokemon_id":"74","min_level":"24","max_level":"24"},{"id":"7189","version_id":"13","location_area_id":"117","encounter_slot_id":"9","pokemon_id":"74","min_level":"24","max_level":"24"},{"id":"7191","version_id":"13","location_area_id":"117","encounter_slot_id":"11","pokemon_id":"74","min_level":"24","max_level":"24"},{"id":"7229","version_id":"13","location_area_id":"120","encounter_slot_id":"1","pokemon_id":"74","min_level":"30","max_level":"30"},{"id":"7233","version_id":"13","location_area_id":"120","encounter_slot_id":"5","pokemon_id":"74","min_level":"29","max_level":"29"},{"id":"7237","version_id":"13","location_area_id":"120","encounter_slot_id":"9","pokemon_id":"74","min_level":"31","max_level":"31"},{"id":"7239","version_id":"13","location_area_id":"120","encounter_slot_id":"11","pokemon_id":"74","min_level":"31","max_level":"31"},{"id":"7261","version_id":"13","location_area_id":"121","encounter_slot_id":"11","pokemon_id":"74","min_level":"31","max_level":"31"},{"id":"7283","version_id":"13","location_area_id":"122","encounter_slot_id":"11","pokemon_id":"74","min_level":"31","max_level":"31"},{"id":"7305","version_id":"13","location_area_id":"123","encounter_slot_id":"11","pokemon_id":"74","min_level":"31","max_level":"31"},{"id":"7327","version_id":"13","location_area_id":"124","encounter_slot_id":"11","pokemon_id":"74","min_level":"32","max_level":"32"},{"id":"7349","version_id":"13","location_area_id":"125","encounter_slot_id":"11","pokemon_id":"74","min_level":"32","max_level":"32"},{"id":"7754","version_id":"13","location_area_id":"139","encounter_slot_id":"2","pokemon_id":"74","min_level":"20","max_level":"20"},{"id":"8111","version_id":"13","location_area_id":"148","encounter_slot_id":"2","pokemon_id":"74","min_level":"14","max_level":"14"},{"id":"8119","version_id":"13","location_area_id":"148","encounter_slot_id":"5","pokemon_id":"74","min_level":"14","max_level":"14"},{"id":"8131","version_id":"13","location_area_id":"148","encounter_slot_id":"10","pokemon_id":"74","min_level":"15","max_level":"15"},{"id":"8132","version_id":"13","location_area_id":"148","encounter_slot_id":"10","pokemon_id":"74","min_level":"15","max_level":"15"},{"id":"8133","version_id":"13","location_area_id":"148","encounter_slot_id":"10","pokemon_id":"74","min_level":"15","max_level":"15"},{"id":"8135","version_id":"13","location_area_id":"148","encounter_slot_id":"10","pokemon_id":"74","min_level":"15","max_level":"15"},{"id":"8136","version_id":"13","location_area_id":"148","encounter_slot_id":"10","pokemon_id":"74","min_level":"15","max_level":"15"},{"id":"8139","version_id":"13","location_area_id":"148","encounter_slot_id":"12","pokemon_id":"74","min_level":"16","max_level":"16"},{"id":"8143","version_id":"13","location_area_id":"149","encounter_slot_id":"2","pokemon_id":"74","min_level":"5","max_level":"5"},{"id":"8151","version_id":"13","location_area_id":"149","encounter_slot_id":"5","pokemon_id":"74","min_level":"6","max_level":"6"},{"id":"8153","version_id":"13","location_area_id":"149","encounter_slot_id":"6","pokemon_id":"74","min_level":"6","max_level":"6"},{"id":"8155","version_id":"13","location_area_id":"149","encounter_slot_id":"7","pokemon_id":"74","min_level":"7","max_level":"7"},{"id":"8156","version_id":"13","location_area_id":"149","encounter_slot_id":"8","pokemon_id":"74","min_level":"7","max_level":"7"},{"id":"8163","version_id":"13","location_area_id":"149","encounter_slot_id":"10","pokemon_id":"74","min_level":"7","max_level":"7"},{"id":"8164","version_id":"13","location_area_id":"149","encounter_slot_id":"10","pokemon_id":"74","min_level":"7","max_level":"7"},{"id":"8165","version_id":"13","location_area_id":"149","encounter_slot_id":"10","pokemon_id":"74","min_level":"7","max_level":"7"},{"id":"8167","version_id":"13","location_area_id":"149","encounter_slot_id":"10","pokemon_id":"74","min_level":"7","max_level":"7"},{"id":"8168","version_id":"13","location_area_id":"149","encounter_slot_id":"10","pokemon_id":"74","min_level":"7","max_level":"7"},{"id":"8171","version_id":"13","location_area_id":"149","encounter_slot_id":"12","pokemon_id":"74","min_level":"7","max_level":"7"},{"id":"8358","version_id":"13","location_area_id":"157","encounter_slot_id":"2","pokemon_id":"74","min_level":"19","max_level":"19"},{"id":"8365","version_id":"13","location_area_id":"157","encounter_slot_id":"5","pokemon_id":"74","min_level":"19","max_level":"19"},{"id":"8445","version_id":"13","location_area_id":"159","encounter_slot_id":"5","pokemon_id":"74","min_level":"13","max_level":"13"},{"id":"8629","version_id":"13","location_area_id":"164","encounter_slot_id":"2","pokemon_id":"74","min_level":"22","max_level":"22"},{"id":"8681","version_id":"13","location_area_id":"165","encounter_slot_id":"2","pokemon_id":"74","min_level":"20","max_level":"20"},{"id":"8686","version_id":"13","location_area_id":"165","encounter_slot_id":"4","pokemon_id":"74","min_level":"21","max_level":"21"},{"id":"8695","version_id":"13","location_area_id":"165","encounter_slot_id":"9","pokemon_id":"74","min_level":"22","max_level":"22"},{"id":"8696","version_id":"13","location_area_id":"165","encounter_slot_id":"9","pokemon_id":"74","min_level":"22","max_level":"22"},{"id":"8697","version_id":"13","location_area_id":"165","encounter_slot_id":"9","pokemon_id":"74","min_level":"22","max_level":"22"},{"id":"8699","version_id":"13","location_area_id":"165","encounter_slot_id":"9","pokemon_id":"74","min_level":"22","max_level":"22"},{"id":"8700","version_id":"13","location_area_id":"165","encounter_slot_id":"9","pokemon_id":"74","min_level":"22","max_level":"22"},{"id":"8707","version_id":"13","location_area_id":"165","encounter_slot_id":"11","pokemon_id":"74","min_level":"22","max_level":"22"},{"id":"9443","version_id":"14","location_area_id":"6","encounter_slot_id":"123","pokemon_id":"74","min_level":"5","max_level":"5"},{"id":"9444","version_id":"14","location_area_id":"6","encounter_slot_id":"124","pokemon_id":"74","min_level":"6","max_level":"6"},{"id":"9447","version_id":"14","location_area_id":"6","encounter_slot_id":"127","pokemon_id":"74","min_level":"4","max_level":"4"},{"id":"9448","version_id":"14","location_area_id":"6","encounter_slot_id":"128","pokemon_id":"74","min_level":"7","max_level":"7"},{"id":"9451","version_id":"14","location_area_id":"6","encounter_slot_id":"131","pokemon_id":"74","min_level":"8","max_level":"8"},{"id":"9453","version_id":"14","location_area_id":"6","encounter_slot_id":"132","pokemon_id":"74","min_level":"7","max_level":"7"},{"id":"9454","version_id":"14","location_area_id":"6","encounter_slot_id":"132","pokemon_id":"74","min_level":"7","max_level":"7"},{"id":"9455","version_id":"14","location_area_id":"6","encounter_slot_id":"132","pokemon_id":"74","min_level":"7","max_level":"7"},{"id":"9456","version_id":"14","location_area_id":"6","encounter_slot_id":"132","pokemon_id":"74","min_level":"7","max_level":"7"},{"id":"9457","version_id":"14","location_area_id":"6","encounter_slot_id":"132","pokemon_id":"74","min_level":"7","max_level":"7"},{"id":"9458","version_id":"14","location_area_id":"6","encounter_slot_id":"133","pokemon_id":"74","min_level":"8","max_level":"8"},{"id":"9460","version_id":"14","location_area_id":"6","encounter_slot_id":"134","pokemon_id":"74","min_level":"7","max_level":"7"},{"id":"9461","version_id":"14","location_area_id":"7","encounter_slot_id":"123","pokemon_id":"74","min_level":"6","max_level":"6"},{"id":"9462","version_id":"14","location_area_id":"7","encounter_slot_id":"124","pokemon_id":"74","min_level":"7","max_level":"7"},{"id":"9465","version_id":"14","location_area_id":"7","encounter_slot_id":"127","pokemon_id":"74","min_level":"5","max_level":"5"},{"id":"9466","version_id":"14","location_area_id":"7","encounter_slot_id":"128","pokemon_id":"74","min_level":"8","max_level":"8"},{"id":"9469","version_id":"14","location_area_id":"7","encounter_slot_id":"131","pokemon_id":"74","min_level":"9","max_level":"9"},{"id":"9471","version_id":"14","location_area_id":"7","encounter_slot_id":"132","pokemon_id":"74","min_level":"8","max_level":"8"},{"id":"9472","version_id":"14","location_area_id":"7","encounter_slot_id":"132","pokemon_id":"74","min_level":"8","max_level":"8"},{"id":"9473","version_id":"14","location_area_id":"7","encounter_slot_id":"132","pokemon_id":"74","min_level":"8","max_level":"8"},{"id":"9474","version_id":"14","location_area_id":"7","encounter_slot_id":"132","pokemon_id":"74","min_level":"8","max_level":"8"},{"id":"9475","version_id":"14","location_area_id":"7","encounter_slot_id":"132","pokemon_id":"74","min_level":"8","max_level":"8"},{"id":"9476","version_id":"14","location_area_id":"7","encounter_slot_id":"133","pokemon_id":"74","min_level":"9","max_level":"9"},{"id":"9478","version_id":"14","location_area_id":"7","encounter_slot_id":"134","pokemon_id":"74","min_level":"8","max_level":"8"},{"id":"9588","version_id":"14","location_area_id":"11","encounter_slot_id":"124","pokemon_id":"74","min_level":"19","max_level":"19"},{"id":"9593","version_id":"14","location_area_id":"11","encounter_slot_id":"126","pokemon_id":"74","min_level":"17","max_level":"17"},{"id":"9902","version_id":"14","location_area_id":"22","encounter_slot_id":"124","pokemon_id":"74","min_level":"15","max_level":"15"},{"id":"9907","version_id":"14","location_area_id":"22","encounter_slot_id":"126","pokemon_id":"74","min_level":"13","max_level":"13"},{"id":"10605","version_id":"14","location_area_id":"55","encounter_slot_id":"127","pokemon_id":"74","min_level":"5","max_level":"5"},{"id":"10608","version_id":"14","location_area_id":"55","encounter_slot_id":"130","pokemon_id":"74","min_level":"7","max_level":"7"},{"id":"10617","version_id":"14","location_area_id":"56","encounter_slot_id":"127","pokemon_id":"74","min_level":"6","max_level":"6"},{"id":"10620","version_id":"14","location_area_id":"56","encounter_slot_id":"130","pokemon_id":"74","min_level":"8","max_level":"8"},{"id":"11923","version_id":"14","location_area_id":"113","encounter_slot_id":"124","pokemon_id":"74","min_level":"18","max_level":"18"},{"id":"11924","version_id":"14","location_area_id":"113","encounter_slot_id":"125","pokemon_id":"74","min_level":"17","max_level":"17"},{"id":"11928","version_id":"14","location_area_id":"113","encounter_slot_id":"129","pokemon_id":"74","min_level":"19","max_level":"19"},{"id":"11929","version_id":"14","location_area_id":"113","encounter_slot_id":"130","pokemon_id":"74","min_level":"20","max_level":"20"},{"id":"11931","version_id":"14","location_area_id":"113","encounter_slot_id":"131","pokemon_id":"74","min_level":"17","max_level":"17"},{"id":"11932","version_id":"14","location_area_id":"113","encounter_slot_id":"131","pokemon_id":"74","min_level":"17","max_level":"17"},{"id":"11933","version_id":"14","location_area_id":"113","encounter_slot_id":"131","pokemon_id":"74","min_level":"17","max_level":"17"},{"id":"11934","version_id":"14","location_area_id":"113","encounter_slot_id":"131","pokemon_id":"74","min_level":"17","max_level":"17"},{"id":"11943","version_id":"14","location_area_id":"113","encounter_slot_id":"133","pokemon_id":"74","min_level":"17","max_level":"17"},{"id":"11946","version_id":"14","location_area_id":"114","encounter_slot_id":"124","pokemon_id":"74","min_level":"18","max_level":"18"},{"id":"11952","version_id":"14","location_area_id":"114","encounter_slot_id":"130","pokemon_id":"74","min_level":"20","max_level":"20"},{"id":"11967","version_id":"14","location_area_id":"115","encounter_slot_id":"123","pokemon_id":"74","min_level":"23","max_level":"23"},{"id":"11968","version_id":"14","location_area_id":"115","encounter_slot_id":"124","pokemon_id":"74","min_level":"22","max_level":"22"},{"id":"11969","version_id":"14","location_area_id":"115","encounter_slot_id":"125","pokemon_id":"74","min_level":"21","max_level":"21"},{"id":"11970","version_id":"14","location_area_id":"115","encounter_slot_id":"126","pokemon_id":"74","min_level":"23","max_level":"23"},{"id":"11971","version_id":"14","location_area_id":"115","encounter_slot_id":"127","pokemon_id":"74","min_level":"23","max_level":"23"},{"id":"11972","version_id":"14","location_area_id":"115","encounter_slot_id":"128","pokemon_id":"74","min_level":"23","max_level":"23"},{"id":"11973","version_id":"14","location_area_id":"115","encounter_slot_id":"129","pokemon_id":"74","min_level":"23","max_level":"23"},{"id":"11974","version_id":"14","location_area_id":"115","encounter_slot_id":"130","pokemon_id":"74","min_level":"23","max_level":"23"},{"id":"11975","version_id":"14","location_area_id":"115","encounter_slot_id":"131","pokemon_id":"74","min_level":"23","max_level":"23"},{"id":"11977","version_id":"14","location_area_id":"115","encounter_slot_id":"133","pokemon_id":"74","min_level":"23","max_level":"23"},{"id":"11979","version_id":"14","location_area_id":"116","encounter_slot_id":"123","pokemon_id":"74","min_level":"24","max_level":"24"},{"id":"11980","version_id":"14","location_area_id":"116","encounter_slot_id":"124","pokemon_id":"74","min_level":"23","max_level":"23"},{"id":"11981","version_id":"14","location_area_id":"116","encounter_slot_id":"125","pokemon_id":"74","min_level":"22","max_level":"22"},{"id":"11982","version_id":"14","location_area_id":"116","encounter_slot_id":"126","pokemon_id":"74","min_level":"24","max_level":"24"},{"id":"11983","version_id":"14","location_area_id":"116","encounter_slot_id":"127","pokemon_id":"74","min_level":"24","max_level":"24"},{"id":"11984","version_id":"14","location_area_id":"116","encounter_slot_id":"128","pokemon_id":"74","min_level":"24","max_level":"24"},{"id":"11985","version_id":"14","location_area_id":"116","encounter_slot_id":"129","pokemon_id":"74","min_level":"24","max_level":"24"},{"id":"11987","version_id":"14","location_area_id":"116","encounter_slot_id":"131","pokemon_id":"74","min_level":"24","max_level":"24"},{"id":"11989","version_id":"14","location_area_id":"116","encounter_slot_id":"133","pokemon_id":"74","min_level":"24","max_level":"24"},{"id":"11991","version_id":"14","location_area_id":"117","encounter_slot_id":"123","pokemon_id":"74","min_level":"25","max_level":"25"},{"id":"11992","version_id":"14","location_area_id":"117","encounter_slot_id":"124","pokemon_id":"74","min_level":"24","max_level":"24"},{"id":"11993","version_id":"14","location_area_id":"117","encounter_slot_id":"125","pokemon_id":"74","min_level":"23","max_level":"23"},{"id":"11994","version_id":"14","location_area_id":"117","encounter_slot_id":"126","pokemon_id":"74","min_level":"25","max_level":"25"},{"id":"11995","version_id":"14","location_area_id":"117","encounter_slot_id":"127","pokemon_id":"74","min_level":"25","max_level":"25"},{"id":"11997","version_id":"14","location_area_id":"117","encounter_slot_id":"129","pokemon_id":"74","min_level":"25","max_level":"25"},{"id":"11999","version_id":"14","location_area_id":"117","encounter_slot_id":"131","pokemon_id":"74","min_level":"25","max_level":"25"},{"id":"12001","version_id":"14","location_area_id":"117","encounter_slot_id":"133","pokemon_id":"74","min_level":"25","max_level":"25"},{"id":"12039","version_id":"14","location_area_id":"120","encounter_slot_id":"123","pokemon_id":"74","min_level":"31","max_level":"31"},{"id":"12043","version_id":"14","location_area_id":"120","encounter_slot_id":"127","pokemon_id":"74","min_level":"32","max_level":"32"},{"id":"12047","version_id":"14","location_area_id":"120","encounter_slot_id":"131","pokemon_id":"74","min_level":"30","max_level":"30"},{"id":"12049","version_id":"14","location_area_id":"120","encounter_slot_id":"133","pokemon_id":"74","min_level":"30","max_level":"30"},{"id":"12803","version_id":"14","location_area_id":"148","encounter_slot_id":"124","pokemon_id":"74","min_level":"16","max_level":"16"},{"id":"12816","version_id":"14","location_area_id":"148","encounter_slot_id":"130","pokemon_id":"74","min_level":"18","max_level":"18"},{"id":"12818","version_id":"14","location_area_id":"148","encounter_slot_id":"132","pokemon_id":"74","min_level":"18","max_level":"18"},{"id":"12821","version_id":"14","location_area_id":"148","encounter_slot_id":"134","pokemon_id":"74","min_level":"18","max_level":"18"},{"id":"12825","version_id":"14","location_area_id":"149","encounter_slot_id":"124","pokemon_id":"74","min_level":"5","max_level":"5"},{"id":"12838","version_id":"14","location_area_id":"149","encounter_slot_id":"130","pokemon_id":"74","min_level":"6","max_level":"6"},{"id":"12840","version_id":"14","location_area_id":"149","encounter_slot_id":"132","pokemon_id":"74","min_level":"7","max_level":"7"},{"id":"12843","version_id":"14","location_area_id":"149","encounter_slot_id":"134","pokemon_id":"74","min_level":"7","max_level":"7"},{"id":"13041","version_id":"14","location_area_id":"157","encounter_slot_id":"124","pokemon_id":"74","min_level":"18","max_level":"18"},{"id":"13294","version_id":"14","location_area_id":"164","encounter_slot_id":"124","pokemon_id":"74","min_level":"21","max_level":"21"},{"id":"14412","version_id":"15","location_area_id":"193","encounter_slot_id":"65","pokemon_id":"74","min_level":"8","max_level":"14"},{"id":"14413","version_id":"15","location_area_id":"193","encounter_slot_id":"66","pokemon_id":"74","min_level":"3","max_level":"6"},{"id":"14487","version_id":"15","location_area_id":"198","encounter_slot_id":"33","pokemon_id":"74","min_level":"6","max_level":"6"},{"id":"14490","version_id":"15","location_area_id":"198","encounter_slot_id":"35","pokemon_id":"74","min_level":"6","max_level":"6"},{"id":"14533","version_id":"15","location_area_id":"199","encounter_slot_id":"33","pokemon_id":"74","min_level":"8","max_level":"8"},{"id":"14536","version_id":"15","location_area_id":"199","encounter_slot_id":"35","pokemon_id":"74","min_level":"8","max_level":"8"},{"id":"14594","version_id":"15","location_area_id":"200","encounter_slot_id":"39","pokemon_id":"74","min_level":"21","max_level":"21"},{"id":"14595","version_id":"15","location_area_id":"200","encounter_slot_id":"40","pokemon_id":"74","min_level":"21","max_level":"21"},{"id":"15781","version_id":"15","location_area_id":"237","encounter_slot_id":"41","pokemon_id":"74","min_level":"14","max_level":"14"},{"id":"15783","version_id":"15","location_area_id":"237","encounter_slot_id":"43","pokemon_id":"74","min_level":"14","max_level":"14"},{"id":"15810","version_id":"15","location_area_id":"238","encounter_slot_id":"33","pokemon_id":"74","min_level":"13","max_level":"13"},{"id":"15813","version_id":"15","location_area_id":"238","encounter_slot_id":"35","pokemon_id":"74","min_level":"13","max_level":"13"},{"id":"15819","version_id":"15","location_area_id":"238","encounter_slot_id":"37","pokemon_id":"74","min_level":"15","max_level":"15"},{"id":"15822","version_id":"15","location_area_id":"238","encounter_slot_id":"38","pokemon_id":"74","min_level":"15","max_level":"15"},{"id":"15840","version_id":"15","location_area_id":"239","encounter_slot_id":"37","pokemon_id":"74","min_level":"31","max_level":"31"},{"id":"15843","version_id":"15","location_area_id":"239","encounter_slot_id":"38","pokemon_id":"74","min_level":"31","max_level":"31"},{"id":"15893","version_id":"15","location_area_id":"240","encounter_slot_id":"41","pokemon_id":"74","min_level":"16","max_level":"16"},{"id":"15895","version_id":"15","location_area_id":"240","encounter_slot_id":"43","pokemon_id":"74","min_level":"16","max_level":"16"},{"id":"16203","version_id":"15","location_area_id":"251","encounter_slot_id":"33","pokemon_id":"74","min_level":"23","max_level":"23"},{"id":"16207","version_id":"15","location_area_id":"251","encounter_slot_id":"35","pokemon_id":"74","min_level":"23","max_level":"23"},{"id":"16250","version_id":"15","location_area_id":"252","encounter_slot_id":"33","pokemon_id":"74","min_level":"3","max_level":"3"},{"id":"16255","version_id":"15","location_area_id":"252","encounter_slot_id":"35","pokemon_id":"74","min_level":"3","max_level":"3"},{"id":"16269","version_id":"15","location_area_id":"252","encounter_slot_id":"39","pokemon_id":"74","min_level":"2","max_level":"2"},{"id":"16270","version_id":"15","location_area_id":"252","encounter_slot_id":"40","pokemon_id":"74","min_level":"2","max_level":"2"},{"id":"16273","version_id":"15","location_area_id":"252","encounter_slot_id":"41","pokemon_id":"74","min_level":"3","max_level":"3"},{"id":"16277","version_id":"15","location_area_id":"252","encounter_slot_id":"43","pokemon_id":"74","min_level":"3","max_level":"3"},{"id":"16279","version_id":"15","location_area_id":"253","encounter_slot_id":"33","pokemon_id":"74","min_level":"3","max_level":"3"},{"id":"16283","version_id":"15","location_area_id":"253","encounter_slot_id":"35","pokemon_id":"74","min_level":"3","max_level":"3"},{"id":"16289","version_id":"15","location_area_id":"253","encounter_slot_id":"37","pokemon_id":"74","min_level":"2","max_level":"2"},{"id":"16292","version_id":"15","location_area_id":"253","encounter_slot_id":"38","pokemon_id":"74","min_level":"2","max_level":"2"},{"id":"16295","version_id":"15","location_area_id":"253","encounter_slot_id":"39","pokemon_id":"74","min_level":"4","max_level":"4"},{"id":"16296","version_id":"15","location_area_id":"253","encounter_slot_id":"40","pokemon_id":"74","min_level":"4","max_level":"4"},{"id":"16302","version_id":"15","location_area_id":"253","encounter_slot_id":"66","pokemon_id":"74","min_level":"8","max_level":"14"},{"id":"16328","version_id":"15","location_area_id":"254","encounter_slot_id":"33","pokemon_id":"74","min_level":"23","max_level":"23"},{"id":"16331","version_id":"15","location_area_id":"254","encounter_slot_id":"35","pokemon_id":"74","min_level":"23","max_level":"23"},{"id":"16786","version_id":"15","location_area_id":"267","encounter_slot_id":"34","pokemon_id":"74","min_level":"19","max_level":"19"},{"id":"17546","version_id":"15","location_area_id":"290","encounter_slot_id":"34","pokemon_id":"74","min_level":"8","max_level":"8"},{"id":"17551","version_id":"15","location_area_id":"290","encounter_slot_id":"36","pokemon_id":"74","min_level":"8","max_level":"8"},{"id":"17567","version_id":"15","location_area_id":"291","encounter_slot_id":"34","pokemon_id":"74","min_level":"8","max_level":"8"},{"id":"17572","version_id":"15","location_area_id":"291","encounter_slot_id":"36","pokemon_id":"74","min_level":"8","max_level":"8"},{"id":"17588","version_id":"15","location_area_id":"292","encounter_slot_id":"34","pokemon_id":"74","min_level":"10","max_level":"10"},{"id":"17593","version_id":"15","location_area_id":"292","encounter_slot_id":"36","pokemon_id":"74","min_level":"10","max_level":"10"},{"id":"17609","version_id":"15","location_area_id":"293","encounter_slot_id":"34","pokemon_id":"74","min_level":"12","max_level":"12"},{"id":"17614","version_id":"15","location_area_id":"293","encounter_slot_id":"36","pokemon_id":"74","min_level":"12","max_level":"12"},{"id":"17629","version_id":"15","location_area_id":"293","encounter_slot_id":"65","pokemon_id":"74","min_level":"12","max_level":"16"},{"id":"17630","version_id":"15","location_area_id":"293","encounter_slot_id":"66","pokemon_id":"74","min_level":"17","max_level":"21"},{"id":"18717","version_id":"15","location_area_id":"319","encounter_slot_id":"65","pokemon_id":"74","min_level":"24","max_level":"32"},{"id":"18839","version_id":"15","location_area_id":"323","encounter_slot_id":"65","pokemon_id":"74","min_level":"22","max_level":"24"},{"id":"18955","version_id":"15","location_area_id":"325","encounter_slot_id":"65","pokemon_id":"74","min_level":"22","max_level":"24"},{"id":"19426","version_id":"16","location_area_id":"193","encounter_slot_id":"65","pokemon_id":"74","min_level":"8","max_level":"14"},{"id":"19427","version_id":"16","location_area_id":"193","encounter_slot_id":"66","pokemon_id":"74","min_level":"3","max_level":"6"},{"id":"19501","version_id":"16","location_area_id":"198","encounter_slot_id":"33","pokemon_id":"74","min_level":"6","max_level":"6"},{"id":"19504","version_id":"16","location_area_id":"198","encounter_slot_id":"35","pokemon_id":"74","min_level":"6","max_level":"6"},{"id":"19547","version_id":"16","location_area_id":"199","encounter_slot_id":"33","pokemon_id":"74","min_level":"8","max_level":"8"},{"id":"19550","version_id":"16","location_area_id":"199","encounter_slot_id":"35","pokemon_id":"74","min_level":"8","max_level":"8"},{"id":"19608","version_id":"16","location_area_id":"200","encounter_slot_id":"39","pokemon_id":"74","min_level":"21","max_level":"21"},{"id":"19609","version_id":"16","location_area_id":"200","encounter_slot_id":"40","pokemon_id":"74","min_level":"21","max_level":"21"},{"id":"20803","version_id":"16","location_area_id":"237","encounter_slot_id":"41","pokemon_id":"74","min_level":"14","max_level":"14"},{"id":"20805","version_id":"16","location_area_id":"237","encounter_slot_id":"43","pokemon_id":"74","min_level":"14","max_level":"14"},{"id":"20832","version_id":"16","location_area_id":"238","encounter_slot_id":"33","pokemon_id":"74","min_level":"13","max_level":"13"},{"id":"20835","version_id":"16","location_area_id":"238","encounter_slot_id":"35","pokemon_id":"74","min_level":"13","max_level":"13"},{"id":"20841","version_id":"16","location_area_id":"238","encounter_slot_id":"37","pokemon_id":"74","min_level":"15","max_level":"15"},{"id":"20844","version_id":"16","location_area_id":"238","encounter_slot_id":"38","pokemon_id":"74","min_level":"15","max_level":"15"},{"id":"20862","version_id":"16","location_area_id":"239","encounter_slot_id":"37","pokemon_id":"74","min_level":"31","max_level":"31"},{"id":"20865","version_id":"16","location_area_id":"239","encounter_slot_id":"38","pokemon_id":"74","min_level":"31","max_level":"31"},{"id":"20915","version_id":"16","location_area_id":"240","encounter_slot_id":"41","pokemon_id":"74","min_level":"16","max_level":"16"},{"id":"20917","version_id":"16","location_area_id":"240","encounter_slot_id":"43","pokemon_id":"74","min_level":"16","max_level":"16"},{"id":"21225","version_id":"16","location_area_id":"251","encounter_slot_id":"33","pokemon_id":"74","min_level":"23","max_level":"23"},{"id":"21229","version_id":"16","location_area_id":"251","encounter_slot_id":"35","pokemon_id":"74","min_level":"23","max_level":"23"},{"id":"21272","version_id":"16","location_area_id":"252","encounter_slot_id":"33","pokemon_id":"74","min_level":"3","max_level":"3"},{"id":"21277","version_id":"16","location_area_id":"252","encounter_slot_id":"35","pokemon_id":"74","min_level":"3","max_level":"3"},{"id":"21291","version_id":"16","location_area_id":"252","encounter_slot_id":"39","pokemon_id":"74","min_level":"2","max_level":"2"},{"id":"21292","version_id":"16","location_area_id":"252","encounter_slot_id":"40","pokemon_id":"74","min_level":"2","max_level":"2"},{"id":"21295","version_id":"16","location_area_id":"252","encounter_slot_id":"41","pokemon_id":"74","min_level":"3","max_level":"3"},{"id":"21299","version_id":"16","location_area_id":"252","encounter_slot_id":"43","pokemon_id":"74","min_level":"3","max_level":"3"},{"id":"21301","version_id":"16","location_area_id":"253","encounter_slot_id":"33","pokemon_id":"74","min_level":"3","max_level":"3"},{"id":"21305","version_id":"16","location_area_id":"253","encounter_slot_id":"35","pokemon_id":"74","min_level":"3","max_level":"3"},{"id":"21311","version_id":"16","location_area_id":"253","encounter_slot_id":"37","pokemon_id":"74","min_level":"2","max_level":"2"},{"id":"21314","version_id":"16","location_area_id":"253","encounter_slot_id":"38","pokemon_id":"74","min_level":"2","max_level":"2"},{"id":"21317","version_id":"16","location_area_id":"253","encounter_slot_id":"39","pokemon_id":"74","min_level":"4","max_level":"4"},{"id":"21318","version_id":"16","location_area_id":"253","encounter_slot_id":"40","pokemon_id":"74","min_level":"4","max_level":"4"},{"id":"21324","version_id":"16","location_area_id":"253","encounter_slot_id":"66","pokemon_id":"74","min_level":"8","max_level":"14"},{"id":"21350","version_id":"16","location_area_id":"254","encounter_slot_id":"33","pokemon_id":"74","min_level":"23","max_level":"23"},{"id":"21353","version_id":"16","location_area_id":"254","encounter_slot_id":"35","pokemon_id":"74","min_level":"23","max_level":"23"},{"id":"21808","version_id":"16","location_area_id":"267","encounter_slot_id":"34","pokemon_id":"74","min_level":"19","max_level":"19"},{"id":"22568","version_id":"16","location_area_id":"290","encounter_slot_id":"34","pokemon_id":"74","min_level":"8","max_level":"8"},{"id":"22573","version_id":"16","location_area_id":"290","encounter_slot_id":"36","pokemon_id":"74","min_level":"8","max_level":"8"},{"id":"22584","version_id":"16","location_area_id":"290","encounter_slot_id":"41","pokemon_id":"74","min_level":"10","max_level":"10"},{"id":"22586","version_id":"16","location_area_id":"290","encounter_slot_id":"43","pokemon_id":"74","min_level":"10","max_level":"10"},{"id":"22589","version_id":"16","location_area_id":"291","encounter_slot_id":"34","pokemon_id":"74","min_level":"8","max_level":"8"},{"id":"22594","version_id":"16","location_area_id":"291","encounter_slot_id":"36","pokemon_id":"74","min_level":"8","max_level":"8"},{"id":"22605","version_id":"16","location_area_id":"291","encounter_slot_id":"41","pokemon_id":"74","min_level":"10","max_level":"10"},{"id":"22607","version_id":"16","location_area_id":"291","encounter_slot_id":"43","pokemon_id":"74","min_level":"10","max_level":"10"},{"id":"22610","version_id":"16","location_area_id":"292","encounter_slot_id":"34","pokemon_id":"74","min_level":"10","max_level":"10"},{"id":"22615","version_id":"16","location_area_id":"292","encounter_slot_id":"36","pokemon_id":"74","min_level":"10","max_level":"10"},{"id":"22631","version_id":"16","location_area_id":"293","encounter_slot_id":"34","pokemon_id":"74","min_level":"12","max_level":"12"},{"id":"22636","version_id":"16","location_area_id":"293","encounter_slot_id":"36","pokemon_id":"74","min_level":"12","max_level":"12"},{"id":"22651","version_id":"16","location_area_id":"293","encounter_slot_id":"65","pokemon_id":"74","min_level":"12","max_level":"16"},{"id":"22652","version_id":"16","location_area_id":"293","encounter_slot_id":"66","pokemon_id":"74","min_level":"17","max_level":"21"},{"id":"23729","version_id":"16","location_area_id":"319","encounter_slot_id":"65","pokemon_id":"74","min_level":"24","max_level":"32"},{"id":"23849","version_id":"16","location_area_id":"323","encounter_slot_id":"65","pokemon_id":"74","min_level":"22","max_level":"24"},{"id":"23965","version_id":"16","location_area_id":"325","encounter_slot_id":"65","pokemon_id":"74","min_level":"22","max_level":"24"},{"id":"24272","version_id":"1","location_area_id":"290","encounter_slot_id":"70","pokemon_id":"74","min_level":"8","max_level":"8"},{"id":"24275","version_id":"1","location_area_id":"290","encounter_slot_id":"73","pokemon_id":"74","min_level":"10","max_level":"10"},{"id":"24281","version_id":"1","location_area_id":"326","encounter_slot_id":"69","pokemon_id":"74","min_level":"7","max_level":"7"},{"id":"24282","version_id":"1","location_area_id":"326","encounter_slot_id":"70","pokemon_id":"74","min_level":"8","max_level":"8"},{"id":"24288","version_id":"1","location_area_id":"326","encounter_slot_id":"76","pokemon_id":"74","min_level":"9","max_level":"9"},{"id":"24290","version_id":"1","location_area_id":"327","encounter_slot_id":"68","pokemon_id":"74","min_level":"9","max_level":"9"},{"id":"24292","version_id":"1","location_area_id":"327","encounter_slot_id":"70","pokemon_id":"74","min_level":"10","max_level":"10"},{"id":"24301","version_id":"1","location_area_id":"293","encounter_slot_id":"69","pokemon_id":"74","min_level":"17","max_level":"17"},{"id":"24303","version_id":"1","location_area_id":"293","encounter_slot_id":"71","pokemon_id":"74","min_level":"16","max_level":"16"},{"id":"24320","version_id":"1","location_area_id":"331","encounter_slot_id":"68","pokemon_id":"74","min_level":"26","max_level":"26"},{"id":"24440","version_id":"1","location_area_id":"332","encounter_slot_id":"68","pokemon_id":"74","min_level":"24","max_level":"24"},{"id":"24460","version_id":"1","location_area_id":"333","encounter_slot_id":"68","pokemon_id":"74","min_level":"26","max_level":"26"},{"id":"24571","version_id":"1","location_area_id":"328","encounter_slot_id":"69","pokemon_id":"74","min_level":"17","max_level":"17"},{"id":"24573","version_id":"1","location_area_id":"328","encounter_slot_id":"71","pokemon_id":"74","min_level":"16","max_level":"16"},{"id":"24578","version_id":"1","location_area_id":"328","encounter_slot_id":"76","pokemon_id":"74","min_level":"18","max_level":"18"},{"id":"24852","version_id":"2","location_area_id":"290","encounter_slot_id":"70","pokemon_id":"74","min_level":"8","max_level":"8"},{"id":"24855","version_id":"2","location_area_id":"290","encounter_slot_id":"73","pokemon_id":"74","min_level":"10","max_level":"10"},{"id":"24861","version_id":"2","location_area_id":"326","encounter_slot_id":"69","pokemon_id":"74","min_level":"7","max_level":"7"},{"id":"24862","version_id":"2","location_area_id":"326","encounter_slot_id":"70","pokemon_id":"74","min_level":"8","max_level":"8"},{"id":"24868","version_id":"2","location_area_id":"326","encounter_slot_id":"76","pokemon_id":"74","min_level":"9","max_level":"9"},{"id":"24870","version_id":"2","location_area_id":"327","encounter_slot_id":"68","pokemon_id":"74","min_level":"9","max_level":"9"},{"id":"24872","version_id":"2","location_area_id":"327","encounter_slot_id":"70","pokemon_id":"74","min_level":"10","max_level":"10"},{"id":"24881","version_id":"2","location_area_id":"293","encounter_slot_id":"69","pokemon_id":"74","min_level":"17","max_level":"17"},{"id":"24883","version_id":"2","location_area_id":"293","encounter_slot_id":"71","pokemon_id":"74","min_level":"16","max_level":"16"},{"id":"24900","version_id":"2","location_area_id":"331","encounter_slot_id":"68","pokemon_id":"74","min_level":"26","max_level":"26"},{"id":"25020","version_id":"2","location_area_id":"332","encounter_slot_id":"68","pokemon_id":"74","min_level":"24","max_level":"24"},{"id":"25040","version_id":"2","location_area_id":"333","encounter_slot_id":"68","pokemon_id":"74","min_level":"26","max_level":"26"},{"id":"25151","version_id":"2","location_area_id":"328","encounter_slot_id":"69","pokemon_id":"74","min_level":"17","max_level":"17"},{"id":"25153","version_id":"2","location_area_id":"328","encounter_slot_id":"71","pokemon_id":"74","min_level":"16","max_level":"16"},{"id":"25158","version_id":"2","location_area_id":"328","encounter_slot_id":"76","pokemon_id":"74","min_level":"18","max_level":"18"},{"id":"25461","version_id":"3","location_area_id":"290","encounter_slot_id":"89","pokemon_id":"74","min_level":"10","max_level":"10"},{"id":"25465","version_id":"3","location_area_id":"290","encounter_slot_id":"93","pokemon_id":"74","min_level":"10","max_level":"10"},{"id":"25472","version_id":"3","location_area_id":"326","encounter_slot_id":"90","pokemon_id":"74","min_level":"10","max_level":"10"},{"id":"25473","version_id":"3","location_area_id":"326","encounter_slot_id":"91","pokemon_id":"74","min_level":"11","max_level":"11"},{"id":"25480","version_id":"3","location_area_id":"327","encounter_slot_id":"88","pokemon_id":"74","min_level":"11","max_level":"11"},{"id":"25490","version_id":"3","location_area_id":"293","encounter_slot_id":"88","pokemon_id":"74","min_level":"16","max_level":"16"},{"id":"25493","version_id":"3","location_area_id":"293","encounter_slot_id":"91","pokemon_id":"74","min_level":"18","max_level":"18"},{"id":"25494","version_id":"3","location_area_id":"293","encounter_slot_id":"92","pokemon_id":"74","min_level":"20","max_level":"20"},{"id":"25509","version_id":"3","location_area_id":"331","encounter_slot_id":"87","pokemon_id":"74","min_level":"26","max_level":"26"},{"id":"25510","version_id":"3","location_area_id":"331","encounter_slot_id":"88","pokemon_id":"74","min_level":"31","max_level":"31"},{"id":"25511","version_id":"3","location_area_id":"331","encounter_slot_id":"89","pokemon_id":"74","min_level":"36","max_level":"36"},{"id":"25514","version_id":"3","location_area_id":"331","encounter_slot_id":"92","pokemon_id":"74","min_level":"41","max_level":"41"},{"id":"25649","version_id":"3","location_area_id":"332","encounter_slot_id":"87","pokemon_id":"74","min_level":"31","max_level":"31"},{"id":"25650","version_id":"3","location_area_id":"332","encounter_slot_id":"88","pokemon_id":"74","min_level":"36","max_level":"36"},{"id":"25651","version_id":"3","location_area_id":"332","encounter_slot_id":"89","pokemon_id":"74","min_level":"41","max_level":"41"},{"id":"25669","version_id":"3","location_area_id":"333","encounter_slot_id":"87","pokemon_id":"74","min_level":"36","max_level":"36"},{"id":"25671","version_id":"3","location_area_id":"333","encounter_slot_id":"89","pokemon_id":"74","min_level":"41","max_level":"41"},{"id":"25673","version_id":"3","location_area_id":"333","encounter_slot_id":"91","pokemon_id":"74","min_level":"46","max_level":"46"},{"id":"25780","version_id":"3","location_area_id":"328","encounter_slot_id":"88","pokemon_id":"74","min_level":"17","max_level":"17"},{"id":"25784","version_id":"3","location_area_id":"328","encounter_slot_id":"92","pokemon_id":"74","min_level":"21","max_level":"21"},{"id":"26883","version_id":"7","location_area_id":"361","encounter_slot_id":"178","pokemon_id":"74","min_level":"7","max_level":"7"},{"id":"26884","version_id":"7","location_area_id":"361","encounter_slot_id":"179","pokemon_id":"74","min_level":"8","max_level":"8"},{"id":"26885","version_id":"7","location_area_id":"361","encounter_slot_id":"180","pokemon_id":"74","min_level":"6","max_level":"6"},{"id":"26886","version_id":"7","location_area_id":"361","encounter_slot_id":"181","pokemon_id":"74","min_level":"9","max_level":"9"},{"id":"26899","version_id":"7","location_area_id":"363","encounter_slot_id":"182","pokemon_id":"74","min_level":"10","max_level":"15"},{"id":"26901","version_id":"7","location_area_id":"363","encounter_slot_id":"184","pokemon_id":"74","min_level":"5","max_level":"10"},{"id":"26902","version_id":"7","location_area_id":"363","encounter_slot_id":"185","pokemon_id":"74","min_level":"15","max_level":"20"},{"id":"26903","version_id":"7","location_area_id":"363","encounter_slot_id":"186","pokemon_id":"74","min_level":"15","max_level":"20"},{"id":"27160","version_id":"7","location_area_id":"383","encounter_slot_id":"183","pokemon_id":"74","min_level":"30","max_level":"40"},{"id":"27517","version_id":"7","location_area_id":"403","encounter_slot_id":"182","pokemon_id":"74","min_level":"10","max_level":"15"},{"id":"27518","version_id":"7","location_area_id":"403","encounter_slot_id":"183","pokemon_id":"74","min_level":"5","max_level":"10"},{"id":"27519","version_id":"7","location_area_id":"403","encounter_slot_id":"184","pokemon_id":"74","min_level":"15","max_level":"20"},{"id":"27520","version_id":"7","location_area_id":"403","encounter_slot_id":"185","pokemon_id":"74","min_level":"15","max_level":"20"},{"id":"27521","version_id":"7","location_area_id":"403","encounter_slot_id":"186","pokemon_id":"74","min_level":"15","max_level":"20"},{"id":"27573","version_id":"7","location_area_id":"406","encounter_slot_id":"182","pokemon_id":"74","min_level":"10","max_level":"15"},{"id":"27574","version_id":"7","location_area_id":"406","encounter_slot_id":"183","pokemon_id":"74","min_level":"5","max_level":"10"},{"id":"27575","version_id":"7","location_area_id":"406","encounter_slot_id":"184","pokemon_id":"74","min_level":"15","max_level":"20"},{"id":"27576","version_id":"7","location_area_id":"406","encounter_slot_id":"185","pokemon_id":"74","min_level":"15","max_level":"20"},{"id":"27577","version_id":"7","location_area_id":"406","encounter_slot_id":"186","pokemon_id":"74","min_level":"15","max_level":"20"},{"id":"28030","version_id":"7","location_area_id":"430","encounter_slot_id":"182","pokemon_id":"74","min_level":"10","max_level":"15"},{"id":"28031","version_id":"7","location_area_id":"430","encounter_slot_id":"183","pokemon_id":"74","min_level":"5","max_level":"10"},{"id":"28032","version_id":"7","location_area_id":"430","encounter_slot_id":"184","pokemon_id":"74","min_level":"15","max_level":"20"},{"id":"28033","version_id":"7","location_area_id":"430","encounter_slot_id":"185","pokemon_id":"74","min_level":"20","max_level":"25"},{"id":"28034","version_id":"7","location_area_id":"430","encounter_slot_id":"186","pokemon_id":"74","min_level":"25","max_level":"30"},{"id":"28334","version_id":"8","location_area_id":"361","encounter_slot_id":"178","pokemon_id":"74","min_level":"7","max_level":"7"},{"id":"28335","version_id":"8","location_area_id":"361","encounter_slot_id":"179","pokemon_id":"74","min_level":"8","max_level":"8"},{"id":"28336","version_id":"8","location_area_id":"361","encounter_slot_id":"180","pokemon_id":"74","min_level":"6","max_level":"6"},{"id":"28337","version_id":"8","location_area_id":"361","encounter_slot_id":"181","pokemon_id":"74","min_level":"9","max_level":"9"},{"id":"28350","version_id":"8","location_area_id":"363","encounter_slot_id":"182","pokemon_id":"74","min_level":"10","max_level":"15"},{"id":"28352","version_id":"8","location_area_id":"363","encounter_slot_id":"184","pokemon_id":"74","min_level":"5","max_level":"10"},{"id":"28353","version_id":"8","location_area_id":"363","encounter_slot_id":"185","pokemon_id":"74","min_level":"15","max_level":"20"},{"id":"28354","version_id":"8","location_area_id":"363","encounter_slot_id":"186","pokemon_id":"74","min_level":"15","max_level":"20"},{"id":"28611","version_id":"8","location_area_id":"383","encounter_slot_id":"183","pokemon_id":"74","min_level":"30","max_level":"40"},{"id":"28968","version_id":"8","location_area_id":"403","encounter_slot_id":"182","pokemon_id":"74","min_level":"10","max_level":"15"},{"id":"28969","version_id":"8","location_area_id":"403","encounter_slot_id":"183","pokemon_id":"74","min_level":"5","max_level":"10"},{"id":"28970","version_id":"8","location_area_id":"403","encounter_slot_id":"184","pokemon_id":"74","min_level":"15","max_level":"20"},{"id":"28971","version_id":"8","location_area_id":"403","encounter_slot_id":"185","pokemon_id":"74","min_level":"15","max_level":"20"},{"id":"28972","version_id":"8","location_area_id":"403","encounter_slot_id":"186","pokemon_id":"74","min_level":"15","max_level":"20"},{"id":"29024","version_id":"8","location_area_id":"406","encounter_slot_id":"182","pokemon_id":"74","min_level":"10","max_level":"15"},{"id":"29025","version_id":"8","location_area_id":"406","encounter_slot_id":"183","pokemon_id":"74","min_level":"5","max_level":"10"},{"id":"29026","version_id":"8","location_area_id":"406","encounter_slot_id":"184","pokemon_id":"74","min_level":"15","max_level":"20"},{"id":"29027","version_id":"8","location_area_id":"406","encounter_slot_id":"185","pokemon_id":"74","min_level":"15","max_level":"20"},{"id":"29028","version_id":"8","location_area_id":"406","encounter_slot_id":"186","pokemon_id":"74","min_level":"15","max_level":"20"},{"id":"29481","version_id":"8","location_area_id":"430","encounter_slot_id":"182","pokemon_id":"74","min_level":"10","max_level":"15"},{"id":"29482","version_id":"8","location_area_id":"430","encounter_slot_id":"183","pokemon_id":"74","min_level":"5","max_level":"10"},{"id":"29483","version_id":"8","location_area_id":"430","encounter_slot_id":"184","pokemon_id":"74","min_level":"15","max_level":"20"},{"id":"29484","version_id":"8","location_area_id":"430","encounter_slot_id":"185","pokemon_id":"74","min_level":"20","max_level":"25"},{"id":"29485","version_id":"8","location_area_id":"430","encounter_slot_id":"186","pokemon_id":"74","min_level":"25","max_level":"30"},{"id":"29707","version_id":"9","location_area_id":"403","encounter_slot_id":"214","pokemon_id":"74","min_level":"10","max_level":"15"},{"id":"29708","version_id":"9","location_area_id":"403","encounter_slot_id":"215","pokemon_id":"74","min_level":"5","max_level":"10"},{"id":"29709","version_id":"9","location_area_id":"403","encounter_slot_id":"216","pokemon_id":"74","min_level":"15","max_level":"20"},{"id":"29710","version_id":"9","location_area_id":"403","encounter_slot_id":"217","pokemon_id":"74","min_level":"15","max_level":"20"},{"id":"29711","version_id":"9","location_area_id":"403","encounter_slot_id":"218","pokemon_id":"74","min_level":"15","max_level":"20"},{"id":"29763","version_id":"9","location_area_id":"406","encounter_slot_id":"214","pokemon_id":"74","min_level":"10","max_level":"15"},{"id":"29764","version_id":"9","location_area_id":"406","encounter_slot_id":"215","pokemon_id":"74","min_level":"5","max_level":"10"},{"id":"29765","version_id":"9","location_area_id":"406","encounter_slot_id":"216","pokemon_id":"74","min_level":"15","max_level":"20"},{"id":"29766","version_id":"9","location_area_id":"406","encounter_slot_id":"217","pokemon_id":"74","min_level":"15","max_level":"20"},{"id":"29767","version_id":"9","location_area_id":"406","encounter_slot_id":"218","pokemon_id":"74","min_level":"15","max_level":"20"},{"id":"29908","version_id":"9","location_area_id":"361","encounter_slot_id":"195","pokemon_id":"74","min_level":"7","max_level":"7"},{"id":"29909","version_id":"9","location_area_id":"361","encounter_slot_id":"196","pokemon_id":"74","min_level":"8","max_level":"8"},{"id":"29910","version_id":"9","location_area_id":"361","encounter_slot_id":"197","pokemon_id":"74","min_level":"6","max_level":"6"},{"id":"29911","version_id":"9","location_area_id":"361","encounter_slot_id":"198","pokemon_id":"74","min_level":"9","max_level":"9"},{"id":"29924","version_id":"9","location_area_id":"363","encounter_slot_id":"214","pokemon_id":"74","min_level":"10","max_level":"15"},{"id":"29926","version_id":"9","location_area_id":"363","encounter_slot_id":"216","pokemon_id":"74","min_level":"5","max_level":"10"},{"id":"29927","version_id":"9","location_area_id":"363","encounter_slot_id":"217","pokemon_id":"74","min_level":"15","max_level":"20"},{"id":"29928","version_id":"9","location_area_id":"363","encounter_slot_id":"218","pokemon_id":"74","min_level":"15","max_level":"20"},{"id":"30062","version_id":"9","location_area_id":"383","encounter_slot_id":"215","pokemon_id":"74","min_level":"30","max_level":"40"},{"id":"30144","version_id":"9","location_area_id":"430","encounter_slot_id":"214","pokemon_id":"74","min_level":"10","max_level":"15"},{"id":"30145","version_id":"9","location_area_id":"430","encounter_slot_id":"215","pokemon_id":"74","min_level":"5","max_level":"10"},{"id":"30146","version_id":"9","location_area_id":"430","encounter_slot_id":"216","pokemon_id":"74","min_level":"15","max_level":"20"},{"id":"30147","version_id":"9","location_area_id":"430","encounter_slot_id":"217","pokemon_id":"74","min_level":"20","max_level":"25"},{"id":"30148","version_id":"9","location_area_id":"430","encounter_slot_id":"218","pokemon_id":"74","min_level":"25","max_level":"30"},{"id":"31062","version_id":"9","location_area_id":"437","encounter_slot_id":"187","pokemon_id":"74","min_level":"27","max_level":"27"},{"id":"31064","version_id":"9","location_area_id":"437","encounter_slot_id":"189","pokemon_id":"74","min_level":"28","max_level":"28"},{"id":"31066","version_id":"9","location_area_id":"437","encounter_slot_id":"191","pokemon_id":"74","min_level":"29","max_level":"29"},{"id":"31067","version_id":"9","location_area_id":"437","encounter_slot_id":"192","pokemon_id":"74","min_level":"30","max_level":"30"},{"id":"31068","version_id":"9","location_area_id":"437","encounter_slot_id":"193","pokemon_id":"74","min_level":"30","max_level":"30"},{"id":"31316","version_id":"10","location_area_id":"458","encounter_slot_id":"221","pokemon_id":"74","min_level":"7","max_level":"7"},{"id":"31319","version_id":"10","location_area_id":"458","encounter_slot_id":"224","pokemon_id":"74","min_level":"8","max_level":"8"},{"id":"31320","version_id":"10","location_area_id":"458","encounter_slot_id":"225","pokemon_id":"74","min_level":"9","max_level":"9"},{"id":"31339","version_id":"10","location_area_id":"460","encounter_slot_id":"220","pokemon_id":"74","min_level":"9","max_level":"9"},{"id":"31342","version_id":"10","location_area_id":"460","encounter_slot_id":"223","pokemon_id":"74","min_level":"10","max_level":"10"},{"id":"31378","version_id":"10","location_area_id":"463","encounter_slot_id":"220","pokemon_id":"74","min_level":"32","max_level":"32"},{"id":"31390","version_id":"10","location_area_id":"464","encounter_slot_id":"220","pokemon_id":"74","min_level":"34","max_level":"34"},{"id":"31402","version_id":"10","location_area_id":"465","encounter_slot_id":"220","pokemon_id":"74","min_level":"32","max_level":"32"},{"id":"31550","version_id":"10","location_area_id":"472","encounter_slot_id":"246","pokemon_id":"74","min_level":"30","max_level":"40"},{"id":"31553","version_id":"10","location_area_id":"472","encounter_slot_id":"249","pokemon_id":"74","min_level":"40","max_level":"50"},{"id":"31554","version_id":"10","location_area_id":"472","encounter_slot_id":"250","pokemon_id":"74","min_level":"40","max_level":"50"},{"id":"31577","version_id":"10","location_area_id":"473","encounter_slot_id":"246","pokemon_id":"74","min_level":"35","max_level":"45"},{"id":"31580","version_id":"10","location_area_id":"473","encounter_slot_id":"249","pokemon_id":"74","min_level":"45","max_level":"55"},{"id":"31581","version_id":"10","location_area_id":"473","encounter_slot_id":"250","pokemon_id":"74","min_level":"45","max_level":"55"},{"id":"31599","version_id":"10","location_area_id":"474","encounter_slot_id":"246","pokemon_id":"74","min_level":"40","max_level":"50"},{"id":"31602","version_id":"10","location_area_id":"474","encounter_slot_id":"249","pokemon_id":"74","min_level":"50","max_level":"60"},{"id":"31603","version_id":"10","location_area_id":"474","encounter_slot_id":"250","pokemon_id":"74","min_level":"50","max_level":"60"},{"id":"31627","version_id":"10","location_area_id":"475","encounter_slot_id":"220","pokemon_id":"74","min_level":"16","max_level":"16"},{"id":"31629","version_id":"10","location_area_id":"475","encounter_slot_id":"222","pokemon_id":"74","min_level":"17","max_level":"17"},{"id":"31634","version_id":"10","location_area_id":"475","encounter_slot_id":"227","pokemon_id":"74","min_level":"15","max_level":"15"},{"id":"31636","version_id":"10","location_area_id":"475","encounter_slot_id":"229","pokemon_id":"74","min_level":"15","max_level":"15"},{"id":"31638","version_id":"10","location_area_id":"476","encounter_slot_id":"246","pokemon_id":"74","min_level":"5","max_level":"20"},{"id":"31639","version_id":"10","location_area_id":"476","encounter_slot_id":"247","pokemon_id":"74","min_level":"10","max_level":"20"},{"id":"31640","version_id":"10","location_area_id":"476","encounter_slot_id":"248","pokemon_id":"74","min_level":"15","max_level":"30"},{"id":"31644","version_id":"10","location_area_id":"476","encounter_slot_id":"220","pokemon_id":"74","min_level":"17","max_level":"17"},{"id":"31646","version_id":"10","location_area_id":"476","encounter_slot_id":"222","pokemon_id":"74","min_level":"16","max_level":"16"},{"id":"31651","version_id":"10","location_area_id":"476","encounter_slot_id":"227","pokemon_id":"74","min_level":"15","max_level":"15"},{"id":"31653","version_id":"10","location_area_id":"476","encounter_slot_id":"229","pokemon_id":"74","min_level":"15","max_level":"15"},{"id":"31817","version_id":"10","location_area_id":"488","encounter_slot_id":"246","pokemon_id":"74","min_level":"5","max_level":"20"},{"id":"31818","version_id":"10","location_area_id":"488","encounter_slot_id":"247","pokemon_id":"74","min_level":"10","max_level":"20"},{"id":"31819","version_id":"10","location_area_id":"488","encounter_slot_id":"248","pokemon_id":"74","min_level":"15","max_level":"30"},{"id":"31827","version_id":"10","location_area_id":"488","encounter_slot_id":"224","pokemon_id":"74","min_level":"33","max_level":"33"},{"id":"31834","version_id":"10","location_area_id":"489","encounter_slot_id":"219","pokemon_id":"74","min_level":"33","max_level":"33"},{"id":"31836","version_id":"10","location_area_id":"489","encounter_slot_id":"221","pokemon_id":"74","min_level":"29","max_level":"29"},{"id":"31837","version_id":"10","location_area_id":"489","encounter_slot_id":"222","pokemon_id":"74","min_level":"31","max_level":"31"},{"id":"31840","version_id":"10","location_area_id":"489","encounter_slot_id":"225","pokemon_id":"74","min_level":"35","max_level":"35"},{"id":"31842","version_id":"10","location_area_id":"489","encounter_slot_id":"227","pokemon_id":"74","min_level":"37","max_level":"37"},{"id":"31844","version_id":"10","location_area_id":"489","encounter_slot_id":"229","pokemon_id":"74","min_level":"37","max_level":"37"},{"id":"31846","version_id":"10","location_area_id":"490","encounter_slot_id":"246","pokemon_id":"74","min_level":"5","max_level":"20"},{"id":"31847","version_id":"10","location_area_id":"490","encounter_slot_id":"247","pokemon_id":"74","min_level":"10","max_level":"20"},{"id":"31848","version_id":"10","location_area_id":"490","encounter_slot_id":"248","pokemon_id":"74","min_level":"15","max_level":"30"},{"id":"31851","version_id":"10","location_area_id":"490","encounter_slot_id":"219","pokemon_id":"74","min_level":"34","max_level":"34"},{"id":"31853","version_id":"10","location_area_id":"490","encounter_slot_id":"221","pokemon_id":"74","min_level":"30","max_level":"30"},{"id":"31854","version_id":"10","location_area_id":"490","encounter_slot_id":"222","pokemon_id":"74","min_level":"32","max_level":"32"},{"id":"31863","version_id":"10","location_area_id":"491","encounter_slot_id":"246","pokemon_id":"74","min_level":"25","max_level":"35"},{"id":"31866","version_id":"10","location_area_id":"491","encounter_slot_id":"249","pokemon_id":"74","min_level":"30","max_level":"40"},{"id":"31867","version_id":"10","location_area_id":"491","encounter_slot_id":"250","pokemon_id":"74","min_level":"30","max_level":"40"},{"id":"31868","version_id":"10","location_area_id":"491","encounter_slot_id":"219","pokemon_id":"74","min_level":"36","max_level":"36"},{"id":"31870","version_id":"10","location_area_id":"491","encounter_slot_id":"221","pokemon_id":"74","min_level":"32","max_level":"32"},{"id":"31871","version_id":"10","location_area_id":"491","encounter_slot_id":"222","pokemon_id":"74","min_level":"34","max_level":"34"},{"id":"31874","version_id":"10","location_area_id":"491","encounter_slot_id":"225","pokemon_id":"74","min_level":"38","max_level":"38"},{"id":"31876","version_id":"10","location_area_id":"491","encounter_slot_id":"227","pokemon_id":"74","min_level":"40","max_level":"40"},{"id":"31878","version_id":"10","location_area_id":"491","encounter_slot_id":"229","pokemon_id":"74","min_level":"40","max_level":"40"},{"id":"31880","version_id":"10","location_area_id":"492","encounter_slot_id":"246","pokemon_id":"74","min_level":"25","max_level":"35"},{"id":"31883","version_id":"10","location_area_id":"492","encounter_slot_id":"249","pokemon_id":"74","min_level":"30","max_level":"40"},{"id":"31884","version_id":"10","location_area_id":"492","encounter_slot_id":"250","pokemon_id":"74","min_level":"30","max_level":"40"},{"id":"31885","version_id":"10","location_area_id":"492","encounter_slot_id":"219","pokemon_id":"74","min_level":"38","max_level":"38"},{"id":"31886","version_id":"10","location_area_id":"492","encounter_slot_id":"220","pokemon_id":"74","min_level":"36","max_level":"36"},{"id":"31887","version_id":"10","location_area_id":"492","encounter_slot_id":"221","pokemon_id":"74","min_level":"34","max_level":"34"},{"id":"31888","version_id":"10","location_area_id":"492","encounter_slot_id":"222","pokemon_id":"74","min_level":"40","max_level":"40"},{"id":"31891","version_id":"10","location_area_id":"492","encounter_slot_id":"225","pokemon_id":"74","min_level":"42","max_level":"42"},{"id":"31893","version_id":"10","location_area_id":"492","encounter_slot_id":"227","pokemon_id":"74","min_level":"42","max_level":"42"},{"id":"31895","version_id":"10","location_area_id":"492","encounter_slot_id":"229","pokemon_id":"74","min_level":"42","max_level":"42"},{"id":"31897","version_id":"10","location_area_id":"493","encounter_slot_id":"246","pokemon_id":"74","min_level":"25","max_level":"35"},{"id":"31900","version_id":"10","location_area_id":"493","encounter_slot_id":"249","pokemon_id":"74","min_level":"30","max_level":"40"},{"id":"31901","version_id":"10","location_area_id":"493","encounter_slot_id":"250","pokemon_id":"74","min_level":"30","max_level":"40"},{"id":"31902","version_id":"10","location_area_id":"493","encounter_slot_id":"219","pokemon_id":"74","min_level":"40","max_level":"40"},{"id":"31904","version_id":"10","location_area_id":"493","encounter_slot_id":"221","pokemon_id":"74","min_level":"42","max_level":"42"},{"id":"31908","version_id":"10","location_area_id":"493","encounter_slot_id":"225","pokemon_id":"74","min_level":"44","max_level":"44"},{"id":"31910","version_id":"10","location_area_id":"493","encounter_slot_id":"227","pokemon_id":"74","min_level":"44","max_level":"44"},{"id":"31912","version_id":"10","location_area_id":"493","encounter_slot_id":"229","pokemon_id":"74","min_level":"44","max_level":"44"},{"id":"32185","version_id":"10","location_area_id":"512","encounter_slot_id":"246","pokemon_id":"74","min_level":"5","max_level":"20"},{"id":"32186","version_id":"10","location_area_id":"512","encounter_slot_id":"247","pokemon_id":"74","min_level":"10","max_level":"20"},{"id":"32187","version_id":"10","location_area_id":"512","encounter_slot_id":"248","pokemon_id":"74","min_level":"15","max_level":"30"},{"id":"32204","version_id":"10","location_area_id":"512","encounter_slot_id":"223","pokemon_id":"74","min_level":"31","max_level":"31"},{"id":"32500","version_id":"10","location_area_id":"527","encounter_slot_id":"246","pokemon_id":"74","min_level":"25","max_level":"35"},{"id":"32503","version_id":"10","location_area_id":"527","encounter_slot_id":"249","pokemon_id":"74","min_level":"30","max_level":"40"},{"id":"32504","version_id":"10","location_area_id":"527","encounter_slot_id":"250","pokemon_id":"74","min_level":"30","max_level":"40"},{"id":"32505","version_id":"10","location_area_id":"527","encounter_slot_id":"219","pokemon_id":"74","min_level":"46","max_level":"46"},{"id":"33359","version_id":"11","location_area_id":"458","encounter_slot_id":"221","pokemon_id":"74","min_level":"7","max_level":"7"},{"id":"33362","version_id":"11","location_area_id":"458","encounter_slot_id":"224","pokemon_id":"74","min_level":"8","max_level":"8"},{"id":"33363","version_id":"11","location_area_id":"458","encounter_slot_id":"225","pokemon_id":"74","min_level":"9","max_level":"9"},{"id":"33382","version_id":"11","location_area_id":"460","encounter_slot_id":"220","pokemon_id":"74","min_level":"9","max_level":"9"},{"id":"33385","version_id":"11","location_area_id":"460","encounter_slot_id":"223","pokemon_id":"74","min_level":"10","max_level":"10"},{"id":"33421","version_id":"11","location_area_id":"573","encounter_slot_id":"220","pokemon_id":"74","min_level":"32","max_level":"32"},{"id":"33433","version_id":"11","location_area_id":"574","encounter_slot_id":"220","pokemon_id":"74","min_level":"34","max_level":"34"},{"id":"33445","version_id":"11","location_area_id":"575","encounter_slot_id":"220","pokemon_id":"74","min_level":"32","max_level":"32"},{"id":"33593","version_id":"11","location_area_id":"472","encounter_slot_id":"246","pokemon_id":"74","min_level":"30","max_level":"40"},{"id":"33596","version_id":"11","location_area_id":"472","encounter_slot_id":"249","pokemon_id":"74","min_level":"40","max_level":"50"},{"id":"33597","version_id":"11","location_area_id":"472","encounter_slot_id":"250","pokemon_id":"74","min_level":"40","max_level":"50"},{"id":"33620","version_id":"11","location_area_id":"473","encounter_slot_id":"246","pokemon_id":"74","min_level":"35","max_level":"45"},{"id":"33623","version_id":"11","location_area_id":"473","encounter_slot_id":"249","pokemon_id":"74","min_level":"45","max_level":"55"},{"id":"33624","version_id":"11","location_area_id":"473","encounter_slot_id":"250","pokemon_id":"74","min_level":"45","max_level":"55"},{"id":"33642","version_id":"11","location_area_id":"474","encounter_slot_id":"246","pokemon_id":"74","min_level":"40","max_level":"50"},{"id":"33645","version_id":"11","location_area_id":"474","encounter_slot_id":"249","pokemon_id":"74","min_level":"50","max_level":"60"},{"id":"33646","version_id":"11","location_area_id":"474","encounter_slot_id":"250","pokemon_id":"74","min_level":"50","max_level":"60"},{"id":"33670","version_id":"11","location_area_id":"475","encounter_slot_id":"220","pokemon_id":"74","min_level":"16","max_level":"16"},{"id":"33672","version_id":"11","location_area_id":"475","encounter_slot_id":"222","pokemon_id":"74","min_level":"17","max_level":"17"},{"id":"33677","version_id":"11","location_area_id":"475","encounter_slot_id":"227","pokemon_id":"74","min_level":"15","max_level":"15"},{"id":"33679","version_id":"11","location_area_id":"475","encounter_slot_id":"229","pokemon_id":"74","min_level":"15","max_level":"15"},{"id":"33681","version_id":"11","location_area_id":"476","encounter_slot_id":"246","pokemon_id":"74","min_level":"5","max_level":"20"},{"id":"33682","version_id":"11","location_area_id":"476","encounter_slot_id":"247","pokemon_id":"74","min_level":"10","max_level":"20"},{"id":"33683","version_id":"11","location_area_id":"476","encounter_slot_id":"248","pokemon_id":"74","min_level":"15","max_level":"30"},{"id":"33687","version_id":"11","location_area_id":"476","encounter_slot_id":"220","pokemon_id":"74","min_level":"17","max_level":"17"},{"id":"33689","version_id":"11","location_area_id":"476","encounter_slot_id":"222","pokemon_id":"74","min_level":"16","max_level":"16"},{"id":"33694","version_id":"11","location_area_id":"476","encounter_slot_id":"227","pokemon_id":"74","min_level":"15","max_level":"15"},{"id":"33696","version_id":"11","location_area_id":"476","encounter_slot_id":"229","pokemon_id":"74","min_level":"15","max_level":"15"},{"id":"33860","version_id":"11","location_area_id":"488","encounter_slot_id":"246","pokemon_id":"74","min_level":"5","max_level":"20"},{"id":"33861","version_id":"11","location_area_id":"488","encounter_slot_id":"247","pokemon_id":"74","min_level":"10","max_level":"20"},{"id":"33862","version_id":"11","location_area_id":"488","encounter_slot_id":"248","pokemon_id":"74","min_level":"15","max_level":"30"},{"id":"33870","version_id":"11","location_area_id":"488","encounter_slot_id":"224","pokemon_id":"74","min_level":"33","max_level":"33"},{"id":"33877","version_id":"11","location_area_id":"489","encounter_slot_id":"219","pokemon_id":"74","min_level":"33","max_level":"33"},{"id":"33879","version_id":"11","location_area_id":"489","encounter_slot_id":"221","pokemon_id":"74","min_level":"29","max_level":"29"},{"id":"33880","version_id":"11","location_area_id":"489","encounter_slot_id":"222","pokemon_id":"74","min_level":"31","max_level":"31"},{"id":"33883","version_id":"11","location_area_id":"489","encounter_slot_id":"225","pokemon_id":"74","min_level":"35","max_level":"35"},{"id":"33885","version_id":"11","location_area_id":"489","encounter_slot_id":"227","pokemon_id":"74","min_level":"37","max_level":"37"},{"id":"33887","version_id":"11","location_area_id":"489","encounter_slot_id":"229","pokemon_id":"74","min_level":"37","max_level":"37"},{"id":"33889","version_id":"11","location_area_id":"490","encounter_slot_id":"246","pokemon_id":"74","min_level":"5","max_level":"20"},{"id":"33890","version_id":"11","location_area_id":"490","encounter_slot_id":"247","pokemon_id":"74","min_level":"10","max_level":"20"},{"id":"33891","version_id":"11","location_area_id":"490","encounter_slot_id":"248","pokemon_id":"74","min_level":"15","max_level":"30"},{"id":"33894","version_id":"11","location_area_id":"490","encounter_slot_id":"219","pokemon_id":"74","min_level":"34","max_level":"34"},{"id":"33896","version_id":"11","location_area_id":"490","encounter_slot_id":"221","pokemon_id":"74","min_level":"30","max_level":"30"},{"id":"33897","version_id":"11","location_area_id":"490","encounter_slot_id":"222","pokemon_id":"74","min_level":"32","max_level":"32"},{"id":"33906","version_id":"11","location_area_id":"491","encounter_slot_id":"246","pokemon_id":"74","min_level":"25","max_level":"35"},{"id":"33909","version_id":"11","location_area_id":"491","encounter_slot_id":"249","pokemon_id":"74","min_level":"30","max_level":"40"},{"id":"33910","version_id":"11","location_area_id":"491","encounter_slot_id":"250","pokemon_id":"74","min_level":"30","max_level":"40"},{"id":"33911","version_id":"11","location_area_id":"491","encounter_slot_id":"219","pokemon_id":"74","min_level":"36","max_level":"36"},{"id":"33913","version_id":"11","location_area_id":"491","encounter_slot_id":"221","pokemon_id":"74","min_level":"32","max_level":"32"},{"id":"33914","version_id":"11","location_area_id":"491","encounter_slot_id":"222","pokemon_id":"74","min_level":"34","max_level":"34"},{"id":"33917","version_id":"11","location_area_id":"491","encounter_slot_id":"225","pokemon_id":"74","min_level":"38","max_level":"38"},{"id":"33919","version_id":"11","location_area_id":"491","encounter_slot_id":"227","pokemon_id":"74","min_level":"40","max_level":"40"},{"id":"33921","version_id":"11","location_area_id":"491","encounter_slot_id":"229","pokemon_id":"74","min_level":"40","max_level":"40"},{"id":"33923","version_id":"11","location_area_id":"492","encounter_slot_id":"246","pokemon_id":"74","min_level":"25","max_level":"35"},{"id":"33926","version_id":"11","location_area_id":"492","encounter_slot_id":"249","pokemon_id":"74","min_level":"30","max_level":"40"},{"id":"33927","version_id":"11","location_area_id":"492","encounter_slot_id":"250","pokemon_id":"74","min_level":"30","max_level":"40"},{"id":"33928","version_id":"11","location_area_id":"492","encounter_slot_id":"219","pokemon_id":"74","min_level":"38","max_level":"38"},{"id":"33929","version_id":"11","location_area_id":"492","encounter_slot_id":"220","pokemon_id":"74","min_level":"36","max_level":"36"},{"id":"33930","version_id":"11","location_area_id":"492","encounter_slot_id":"221","pokemon_id":"74","min_level":"34","max_level":"34"},{"id":"33931","version_id":"11","location_area_id":"492","encounter_slot_id":"222","pokemon_id":"74","min_level":"40","max_level":"40"},{"id":"33934","version_id":"11","location_area_id":"492","encounter_slot_id":"225","pokemon_id":"74","min_level":"42","max_level":"42"},{"id":"33936","version_id":"11","location_area_id":"492","encounter_slot_id":"227","pokemon_id":"74","min_level":"42","max_level":"42"},{"id":"33938","version_id":"11","location_area_id":"492","encounter_slot_id":"229","pokemon_id":"74","min_level":"42","max_level":"42"},{"id":"33940","version_id":"11","location_area_id":"493","encounter_slot_id":"246","pokemon_id":"74","min_level":"25","max_level":"35"},{"id":"33943","version_id":"11","location_area_id":"493","encounter_slot_id":"249","pokemon_id":"74","min_level":"30","max_level":"40"},{"id":"33944","version_id":"11","location_area_id":"493","encounter_slot_id":"250","pokemon_id":"74","min_level":"30","max_level":"40"},{"id":"33945","version_id":"11","location_area_id":"493","encounter_slot_id":"219","pokemon_id":"74","min_level":"40","max_level":"40"},{"id":"33947","version_id":"11","location_area_id":"493","encounter_slot_id":"221","pokemon_id":"74","min_level":"42","max_level":"42"},{"id":"33951","version_id":"11","location_area_id":"493","encounter_slot_id":"225","pokemon_id":"74","min_level":"44","max_level":"44"},{"id":"33953","version_id":"11","location_area_id":"493","encounter_slot_id":"227","pokemon_id":"74","min_level":"44","max_level":"44"},{"id":"33955","version_id":"11","location_area_id":"493","encounter_slot_id":"229","pokemon_id":"74","min_level":"44","max_level":"44"},{"id":"34228","version_id":"11","location_area_id":"512","encounter_slot_id":"246","pokemon_id":"74","min_level":"5","max_level":"20"},{"id":"34229","version_id":"11","location_area_id":"512","encounter_slot_id":"247","pokemon_id":"74","min_level":"10","max_level":"20"},{"id":"34230","version_id":"11","location_area_id":"512","encounter_slot_id":"248","pokemon_id":"74","min_level":"15","max_level":"30"},{"id":"34247","version_id":"11","location_area_id":"512","encounter_slot_id":"223","pokemon_id":"74","min_level":"31","max_level":"31"},{"id":"34543","version_id":"11","location_area_id":"527","encounter_slot_id":"246","pokemon_id":"74","min_level":"25","max_level":"35"},{"id":"34546","version_id":"11","location_area_id":"527","encounter_slot_id":"249","pokemon_id":"74","min_level":"30","max_level":"40"},{"id":"34547","version_id":"11","location_area_id":"527","encounter_slot_id":"250","pokemon_id":"74","min_level":"30","max_level":"40"},{"id":"34548","version_id":"11","location_area_id":"527","encounter_slot_id":"219","pokemon_id":"74","min_level":"46","max_level":"46"}]