[{"id":"36898","version_id":"17","location_area_id":"628","encounter_slot_id":"285","pokemon_id":"568","min_level":"22","max_level":"22"},{"id":"36899","version_id":"17","location_area_id":"628","encounter_slot_id":"286","pokemon_id":"568","min_level":"24","max_level":"24"},{"id":"36922","version_id":"17","location_area_id":"628","encounter_slot_id":"273","pokemon_id":"568","min_level":"19","max_level":"19"},{"id":"36923","version_id":"17","location_area_id":"628","encounter_slot_id":"274","pokemon_id":"568","min_level":"21","max_level":"21"},{"id":"37772","version_id":"17","location_area_id":"651","encounter_slot_id":"285","pokemon_id":"568","min_level":"22","max_level":"22"},{"id":"37773","version_id":"17","location_area_id":"651","encounter_slot_id":"286","pokemon_id":"568","min_level":"24","max_level":"24"},{"id":"37796","version_id":"17","location_area_id":"651","encounter_slot_id":"273","pokemon_id":"568","min_level":"19","max_level":"19"},{"id":"37797","version_id":"17","location_area_id":"651","encounter_slot_id":"274","pokemon_id":"568","min_level":"21","max_level":"21"},{"id":"39552","version_id":"18","location_area_id":"628","encounter_slot_id":"285","pokemon_id":"568","min_level":"22","max_level":"22"},{"id":"39553","version_id":"18","location_area_id":"628","encounter_slot_id":"286","pokemon_id":"568","min_level":"24","max_level":"24"},{"id":"39576","version_id":"18","location_area_id":"628","encounter_slot_id":"273","pokemon_id":"568","min_level":"19","max_level":"19"},{"id":"39577","version_id":"18","location_area_id":"628","encounter_slot_id":"274","pokemon_id":"568","min_level":"21","max_level":"21"},{"id":"40426","version_id":"18","location_area_id":"651","encounter_slot_id":"285","pokemon_id":"568","min_level":"22","max_level":"22"},{"id":"40427","version_id":"18","location_area_id":"651","encounter_slot_id":"286","pokemon_id":"568","min_level":"24","max_level":"24"},{"id":"40450","version_id":"18","location_area_id":"651","encounter_slot_id":"273","pokemon_id":"568","min_level":"19","max_level":"19"},{"id":"40451","version_id":"18","location_area_id":"651","encounter_slot_id":"274","pokemon_id":"568","min_level":"21","max_level":"21"},{"id":"43122","version_id":"21","location_area_id":"627","encounter_slot_id":"379","pokemon_id":"568","min_level":"15","max_level":"15"},{"id":"43123","version_id":"21","location_area_id":"627","encounter_slot_id":"380","pokemon_id":"568","min_level":"14","max_level":"14"},{"id":"43125","version_id":"21","location_area_id":"627","encounter_slot_id":"382","pokemon_id":"568","min_level":"17","max_level":"17"},{"id":"43132","version_id":"21","location_area_id":"628","encounter_slot_id":"353","pokemon_id":"568","min_level":"23","max_level":"23"},{"id":"43133","version_id":"21","location_area_id":"628","encounter_slot_id":"354","pokemon_id":"568","min_level":"25","max_level":"25"},{"id":"43156","version_id":"21","location_area_id":"628","encounter_slot_id":"377","pokemon_id":"568","min_level":"21","max_level":"21"},{"id":"43157","version_id":"21","location_area_id":"628","encounter_slot_id":"378","pokemon_id":"568","min_level":"23","max_level":"23"},{"id":"43896","version_id":"21","location_area_id":"651","encounter_slot_id":"353","pokemon_id":"568","min_level":"23","max_level":"23"},{"id":"43897","version_id":"21","location_area_id":"651","encounter_slot_id":"354","pokemon_id":"568","min_level":"25","max_level":"25"},{"id":"43920","version_id":"21","location_area_id":"651","encounter_slot_id":"377","pokemon_id":"568","min_level":"21","max_level":"21"},{"id":"43921","version_id":"21","location_area_id":"651","encounter_slot_id":"378","pokemon_id":"568","min_level":"23","max_level":"23"},{"id":"46852","version_id":"22","location_area_id":"628","encounter_slot_id":"353","pokemon_id":"568","min_level":"23","max_level":"23"},{"id":"46856","version_id":"22","location_area_id":"628","encounter_slot_id":"357","pokemon_id":"568","min_level":"24","max_level":"24"},{"id":"46858","version_id":"22","location_area_id":"628","encounter_slot_id":"359","pokemon_id":"568","min_level":"25","max_level":"25"},{"id":"46860","version_id":"22","location_area_id":"628","encounter_slot_id":"361","pokemon_id":"568","min_level":"26","max_level":"26"},{"id":"46876","version_id":"22","location_area_id":"628","encounter_slot_id":"377","pokemon_id":"568","min_level":"21","max_level":"21"},{"id":"46880","version_id":"22","location_area_id":"628","encounter_slot_id":"381","pokemon_id":"568","min_level":"22","max_level":"22"},{"id":"46882","version_id":"22","location_area_id":"628","encounter_slot_id":"383","pokemon_id":"568","min_level":"23","max_level":"23"},{"id":"46884","version_id":"22","location_area_id":"628","encounter_slot_id":"385","pokemon_id":"568","min_level":"24","max_level":"24"},{"id":"47616","version_id":"22","location_area_id":"651","encounter_slot_id":"353","pokemon_id":"568","min_level":"23","max_level":"23"},{"id":"47620","version_id":"22","location_area_id":"651","encounter_slot_id":"357","pokemon_id":"568","min_level":"24","max_level":"24"},{"id":"47622","version_id":"22","location_area_id":"651","encounter_slot_id":"359","pokemon_id":"568","min_level":"25","max_level":"25"},{"id":"47624","version_id":"22","location_area_id":"651","encounter_slot_id":"361","pokemon_id":"568","min_level":"26","max_level":"26"},{"id":"47640","version_id":"22","location_area_id":"651","encounter_slot_id":"377","pokemon_id":"568","min_level":"21","max_level":"21"},{"id":"47644","version_id":"22","location_area_id":"651","encounter_slot_id":"381","pokemon_id":"568","min_level":"22","max_level":"22"},{"id":"47646","version_id":"22","location_area_id":"651","encounter_slot_id":"383","pokemon_id":"568","min_level":"23","max_level":"23"},{"id":"47648","version_id":"22","location_area_id":"651","encounter_slot_id":"385","pokemon_id":"568","min_level":"24","max_level":"24"}]